[
  {
    "uuid": "b66af4d9e463758f1fbc5081e941d06e3bd76cd2bd97b966a00a0aed83131aaa",
    "source": "PANews",
    "title": "BTC突破7万美元，日内涨幅1.74%",
    "original_url": "https://www.panewslab.com/zh/articles/019c3c63-062a-70f1-a1fc-0f93c4eb11be",
    "publish_ts": 1770539580,
    "content_markdown": "Published Time: 2026-02-08T08:33:00.000Z\n\n[![Image 1](https://www.panewslab.com/_/assets/v2/static/brand.DTYk2FHC.png)](https://www.panewslab.com/zh)\n\n*   [首页](https://www.panewslab.com/zh)\n*   [深度](https://www.panewslab.com/zh/in-depth)\n*   [快讯](https://www.panewslab.com/zh/newsflash)\n*   [事件日历](https://www.panewslab.com/zh/calendar)\n*   [专题](https://www.panewslab.com/zh/series)\n*   [导航](https://www.panewslab.com/zh/tools)\n*   [数据](https://www.panewslab.com/zh/padata/industry)\n*   发现\n\n[](https://www.panewslab.com/zh/search)\n\n### BTC突破7万美元，日内涨幅1.74%\n\n[![Image 2: PA一线](https://image.panewslab.com/upload/image/20210202/S12ce6bd0b5c8479a8e53551c85d68ad7.jpg)](https://www.panewslab.com/zh/columns/166)\n\n[PA一线](https://www.panewslab.com/zh/columns/166)\n\nPANews 2月8日消息，欧易 OKX 行情显示，BTC 突破 7 万美元，现报 70477 美元/枚，日内涨幅 1.74%。\n\n分享至：\n\n作者：PA一线\n\n本内容只为提供市场信息，不构成投资建议。\n\n关注PANews官方账号，一起穿越牛熊\n\nPANews微信群\n\n[Telegram交流群](https://t.me/PANewsLab)[Telegram资讯频道](https://t.me/ChannelPANews)[@PANews](https://x.com/PANews)\n\n热搜:[比特币](https://www.panewslab.com/zh/search?query=%E6%AF%94%E7%89%B9%E5%B8%81)[以太坊](https://www.panewslab.com/zh/search?query=%E4%BB%A5%E5%A4%AA%E5%9D%8A)[稳定币](https://www.panewslab.com/zh/search?query=%E7%A8%B3%E5%AE%9A%E5%B8%81)[预测市场](https://www.panewslab.com/zh/search?query=%E9%A2%84%E6%B5%8B%E5%B8%82%E5%9C%BA)[特朗普](https://www.panewslab.com/zh/search?query=%E7%89%B9%E6%9C%97%E6%99%AE)[币安](https://www.panewslab.com/zh/search?query=%E5%B8%81%E5%AE%89)[OKX](https://www.panewslab.com/zh/search?query=OKX)[USDT](https://www.panewslab.com/zh/search?query=USDT)[DeFi](https://www.panewslab.com/zh/search?query=DeFi)[AI](https://www.panewslab.com/zh/search?query=AI)[美联储主席](https://www.panewslab.com/zh/search?query=%E7%BE%8E%E8%81%94%E5%82%A8%E4%B8%BB%E5%B8%AD)\n\n### 热门文章\n\n[](https://www.panewslab.com/zh/articles/hot)\n\n[小龙虾社交，一个浪费算力的人造“僵尸网络”](https://www.panewslab.com/zh/articles/1f0ecad1-66a6-4297-b4d9-dde7a9f9c980)\n\n[PA荐读](https://www.panewslab.com/zh/columns/1585194023472091)\n\n[矿工正在经历“至暗时刻”，关机还是自救？](https://www.panewslab.com/zh/articles/20ecd95d-a660-4cbb-81f3-3ec35b9e0316)\n\n[PA荐读](https://www.panewslab.com/zh/columns/1585194023472091)\n\n[AI “超级管家”OpenClaw的8大应用场景深度测评](https://www.panewslab.com/zh/articles/41194068-8a6b-4b33-bd6b-7b878e509e04)\n\n[Biteye](https://www.panewslab.com/zh/columns/vg3iy2ar)\n\n[没有黑天鹅，比特币超卖“元凶”的四个非典型猜测](https://www.panewslab.com/zh/articles/6d41eee4-dd92-4dd8-831b-e02b0a7ff2da)\n\n[Nancy](https://www.panewslab.com/zh/columns/N7042814)\n\n[6.5万美元下方的深渊凝视：解构微策略的清算恐慌与2026年宏观生机](https://www.panewslab.com/zh/articles/c39305e0-6b96-4ee5-bf43-d66428c65967)\n\n[Max.S](https://www.panewslab.com/zh/columns/N3144584)\n\n![Image 3](https://www.panewslab.com/_/assets/v2/static/subscribe-us-left.9ODLT9br.png)\n\n行业要闻\n\n市场热点\n\n精选读物\n\n[点击订阅](https://panewscn.substack.com/)\n\n![Image 4](https://www.panewslab.com/_/assets/v2/static/brand.DTYk2FHC.png)\n\n邮件订阅 订阅我们\n\nPANews\n\n[关于我们](https://www.panewslab.com/zh/about)[联系我们](mailto:panews@panony.com)[视觉文档](https://www.panewslab.com/brandingassets)[工作机会](https://panony.com/cn/col.jsp?id=111)[隐私政策](https://www.panewslab.com/zh/privacy-policy)[用户协议](https://www.panewslab.com/zh/user-agreement)\n\n推荐\n\n[事件日历](https://www.panewslab.com/zh/calendar/index.html)[热门活动](https://www.panewslab.com/zh/events)[RSS订阅](https://www.panewslab.com/zh/rss)[申请专栏](https://www.panewslab.com/zh/columns/apply)[行业数据](https://www.panewslab.com/zh/padata/industry)[工具导航](https://www.panewslab.com/zh/tools)\n\n下载APP\n\n[![Image 5](https://www.panewslab.com/_/assets/v2/static/dl-app-store.Y85Fwhjc.png)](https://apps.apple.com/cn/app/id1543133117)[![Image 6](https://www.panewslab.com/_/assets/v2/static/dl-google-play.Db0ECPXB.png)](https://play.google.com/store/apps/details?id=shanghai.panewsApp.com)[Android](https://assets.panewslab.com/panews-android.apk)\n\n关注我们\n\n[](https://x.com/PANews)[](https://t.me/ChannelPANews)[](https://t.me/PANewsLab)[](https://discord.com/invite/panewsdao)[](https://www.xiaohongshu.com/user/profile/6392f3930000000026004851)[](https://space.bilibili.com/455757159)[](https://www.xiaoyuzhoufm.com/podcast/633519d54eda304b8a9e1f0c)[](https://www.threads.com/@panews_lab)\n\n[@沪ICP备19004913号](https://beian.miit.gov.cn/#/)\n",
    "tags": [],
    "status": "success"
  },
  {
    "uuid": "e9a3f6bb2fbd1b9cb27a37ead1956a923970959dee563d4b8c78a47ed96405ed",
    "source": "PANews",
    "title": "在Multicoin干了三年，怎么看“喊单王”Kyle宣布退圈",
    "original_url": "https://www.panewslab.com/zh/articles/019c3bc7-149e-776b-9721-b808905ac99a",
    "publish_ts": 1770537600,
    "content_markdown": "Published Time: 2026-02-08T08:00:00.000Z\n\n[![Image 1](https://www.panewslab.com/_/assets/v2/static/brand.DTYk2FHC.png)](https://www.panewslab.com/zh)\n\n*   [首页](https://www.panewslab.com/zh)\n*   [深度](https://www.panewslab.com/zh/in-depth)\n*   [快讯](https://www.panewslab.com/zh/newsflash)\n*   [事件日历](https://www.panewslab.com/zh/calendar)\n*   [专题](https://www.panewslab.com/zh/series)\n*   [导航](https://www.panewslab.com/zh/tools)\n*   [数据](https://www.panewslab.com/zh/padata/industry)\n*   发现\n\n[](https://www.panewslab.com/zh/search)\n\n### 在Multicoin干了三年，怎么看“喊单王”Kyle宣布退圈\n\n[![Image 2: 链捕手 ChainCatcher](https://image.panewslab.com/upload/image/20220308/20220308165605_349.jpg)](https://www.panewslab.com/zh/columns/1604853782940384)\n\n[链捕手 ChainCatcher](https://www.panewslab.com/zh/columns/1604853782940384)\n\n*   Kyle Samani的投资哲学专注于非共识押注，例如早期支持Solana构建“链上纳斯达克”。\n*   Multicoin Capital错过了永续合约去中心化交易所，因为这些已变为共识领域，不再符合非对称策略。\n*   Kyle现在转向数据类公司，寻求新的非对称机会，而非管理传统基金。\n*   作者Mable Jiang相信团队优势在链上交易、人工智能和合规性，对Multicoin未来保持信心。\n*   她本人专注于构建资产生成协议，强调人生中应全力玩好自己擅长的游戏。\n\n总结\n\n展开\n\n**作者：[mable.sol](https://x.com/mablejiang/status/2019454366739231178)（前 Multicoin Capital 合伙人 Mable Jiang）**\n\n**编译：Ken, Chaincatcher**\n\n每个人只能擅长一种游戏。你应该花一半的时间去弄清楚自己擅长什么游戏，另一半时间则全神贯注地把它玩好。\n\nKyle Samani 很清楚他的游戏是什么。\n\n他的策略是先构思理论，再寻找合适的项目——并且坚持等待理论验证（同时时不时地评估理论是否依然成立）。在利用 Solana 建立“链上纳斯达克”这方面，他从一开始就看到了这个论点（即便当下 Solana 距此愿景尚有距离，但这并非重点），并通过领投多轮融资来执行这一策略——甚至在 SOL 上线主网测试版很久之后，依然参与折价场外轮次。他竭尽所能促成 Solana 的发展。\n\n他的核心博弈在于寻找非对称机会，即非共识押注。Haseeb说得对：在这方面可能没人比 Kyle 更擅长了。\n\n人们质疑为什么 Multicoin 在本周期没有捕捉到任何永续合约去中心化交易所的头部项目或相关基础设施。没有人比我更清楚，Multicoin 在本周期任何事物存在之前，就已经是永续合约去中心化交易所的坚定看多者了。甚至在行业内许多人还没理解中央限价订单簿是如何运作之前——你会感到惊讶，但这确实是事实，毕竟我们许多人最初是密码朋克，后来才适应成为交易专家的（笑）。Multicoin 仔细研究了基本上每一个永续合约去中心化交易所，并分析了其中的权衡取舍。关于设计空间，以及为什么某些设计更好，曾有很多相关博文——你可以在 multicoin.capital 上找到。\n\n那么他们为什么“错过”了呢？因为永续合约去中心化交易所和链上流动性——这些不再是非共识押注了。当然，它们仍有巨大的增长潜力。但共识押注对 Kyle 来说毫无吸引力。那从来都不是他的游戏。\n\n而且对于一个基金来说，目标是为有限合伙人赚钱。因此，循规蹈矩地管理好一个基金不再是 Kyle 想要专注于玩的游戏。经营一家数据类公司可能是他感兴趣的——这在以前从未有人成功做到过（如果你感兴趣，大概可以去听听我在 FWRD 上和他做的那期播客）。世界上还有许多非对称机会等待被发现。Kyle 知道他的游戏是什么，所以他决定专注于玩他擅长且感兴趣的游戏。\n\n没人需要担心谁会转向其他领域。当你清楚自己的游戏是什么时，你就应该专注于玩好它并以赢为目标。赢本身并不是全部目的，但制定取胜策略却是游戏体验的一部分。\n\n许多人担心没有 Kyle 的 Multicoin 会是什么样子。但我并不担心，因为我知道摆在我们所有人面前的机会，正是 Tushar、Brian、Spencer、Shayon、Vishal、Matt、Greg 以及团队其余成员的优势所在：链上交易、人工智能和合规性。只要团队专注于正确地玩这场游戏，它就依然是行业顶尖的。\n\n对我来说，我做实干家已经快四年了。回首往事，我在 Multicoin 的时光是独一无二的——在投资委员会会议上与 Kyle 激烈辩论，与 Tushar 进行战略思想交流，并与每一位投资委员会成员探索许多事物的设计空间。我知道我无法像他们中的任何一个那样优秀，但我也找到了我的热情所在和属于我的游戏领域。\n\n对 Kyle 来说，Web3 的梦想不过变成了冰冷的账本。对我而言，在这个高度商品化的世界里，这些账本凝结了真实的价值传输。当其他所有的筛选机制都彻底失效时，金钱便成了世界上唯一能用来表达观点的相对稀缺资源——而在不久的将来，恐怕连金钱本身也算不上了。这就是为什么我正在构建资产生成协议 （@trendsdotfun）。\n\n我和他从来不需要在玩什么游戏上达成一致。但我们真心希望对方一切顺利，并将在场边为对方喝彩。\n\n人生只有一次，专注于你最擅长的游戏。\n\n我虽然只是在玩游戏，但我玩是为了赢。\n\n放轻松，但也别松懈。\n\n分享至：\n\n作者：链捕手 ChainCatcher\n\n本文为PANews入驻专栏作者的观点，不代表PANews立场，不承担法律责任。\n\n文章及观点也不构成投资意见\n\n图片来源：链捕手 ChainCatcher如有侵权，请联系作者删除。\n\n关注PANews官方账号，一起穿越牛熊\n\nPANews微信群\n\n[Telegram交流群](https://t.me/PANewsLab)[Telegram资讯频道](https://t.me/ChannelPANews)[@PANews](https://x.com/PANews)\n\n热搜:[比特币](https://www.panewslab.com/zh/search?query=%E6%AF%94%E7%89%B9%E5%B8%81)[以太坊](https://www.panewslab.com/zh/search?query=%E4%BB%A5%E5%A4%AA%E5%9D%8A)[稳定币](https://www.panewslab.com/zh/search?query=%E7%A8%B3%E5%AE%9A%E5%B8%81)[预测市场](https://www.panewslab.com/zh/search?query=%E9%A2%84%E6%B5%8B%E5%B8%82%E5%9C%BA)[特朗普](https://www.panewslab.com/zh/search?query=%E7%89%B9%E6%9C%97%E6%99%AE)[币安](https://www.panewslab.com/zh/search?query=%E5%B8%81%E5%AE%89)[OKX](https://www.panewslab.com/zh/search?query=OKX)[USDT](https://www.panewslab.com/zh/search?query=USDT)[DeFi](https://www.panewslab.com/zh/search?query=DeFi)[AI](https://www.panewslab.com/zh/search?query=AI)[美联储主席](https://www.panewslab.com/zh/search?query=%E7%BE%8E%E8%81%94%E5%82%A8%E4%B8%BB%E5%B8%AD)\n\n![Image 3](https://www.panewslab.com/_/assets/v2/static/subscribe-us-left.9ODLT9br.png)\n\n行业要闻\n\n市场热点\n\n精选读物\n\n[点击订阅](https://panewscn.substack.com/)\n\n![Image 4](https://www.panewslab.com/_/assets/v2/static/brand.DTYk2FHC.png)\n\n邮件订阅 订阅我们\n\nPANews\n\n[关于我们](https://www.panewslab.com/zh/about)[联系我们](mailto:panews@panony.com)[视觉文档](https://www.panewslab.com/brandingassets)[工作机会](https://panony.com/cn/col.jsp?id=111)[隐私政策](https://www.panewslab.com/zh/privacy-policy)[用户协议](https://www.panewslab.com/zh/user-agreement)\n\n推荐\n\n[事件日历](https://www.panewslab.com/zh/calendar/index.html)[热门活动](https://www.panewslab.com/zh/events)[RSS订阅](https://www.panewslab.com/zh/rss)[申请专栏](https://www.panewslab.com/zh/columns/apply)[行业数据](https://www.panewslab.com/zh/padata/industry)[工具导航](https://www.panewslab.com/zh/tools)\n\n下载APP\n\n[![Image 5](https://www.panewslab.com/_/assets/v2/static/dl-app-store.Y85Fwhjc.png)](https://apps.apple.com/cn/app/id1543133117)[![Image 6](https://www.panewslab.com/_/assets/v2/static/dl-google-play.Db0ECPXB.png)](https://play.google.com/store/apps/details?id=shanghai.panewsApp.com)[Android](https://assets.panewslab.com/panews-android.apk)\n\n关注我们\n\n[](https://x.com/PANews)[](https://t.me/ChannelPANews)[](https://t.me/PANewsLab)[](https://discord.com/invite/panewsdao)[](https://www.xiaohongshu.com/user/profile/6392f3930000000026004851)[](https://space.bilibili.com/455757159)[](https://www.xiaoyuzhoufm.com/podcast/633519d54eda304b8a9e1f0c)[](https://www.threads.com/@panews_lab)\n\n[@沪ICP备19004913号](https://beian.miit.gov.cn/#/)\n",
    "tags": [],
    "status": "success"
  },
  {
    "uuid": "deb2b58acc483378fe74c1f832b0e3b95b220aeacd5dab779c09e220cd4dd23f",
    "source": "PANews",
    "title": "Arthur Hayes向WinterMute转入ENA、 PENDLE、ETHFI代币",
    "original_url": "https://www.panewslab.com/zh/articles/019c3c30-e929-77df-83a4-2fa98fb19fe5",
    "publish_ts": 1770536340,
    "content_markdown": "",
    "tags": [],
    "status": "partial_content"
  },
  {
    "uuid": "a36b43a90073bd333cbf25c0d19ff3fcf02f4b91aa7efecdbc8c97041aa790f0",
    "source": "PANews",
    "title": "单日ETH合约交易量Bybit排第一，同比增长354.01%",
    "original_url": "https://www.panewslab.com/zh/articles/019c3be9-5025-73f8-bbf6-052a1554f0ba",
    "publish_ts": 1770531660,
    "content_markdown": "Published Time: 2026-02-08T06:21:00.000Z\n\n[![Image 1](https://www.panewslab.com/_/assets/v2/static/brand.DTYk2FHC.png)](https://www.panewslab.com/zh)\n\n*   [首页](https://www.panewslab.com/zh)\n*   [深度](https://www.panewslab.com/zh/in-depth)\n*   [快讯](https://www.panewslab.com/zh/newsflash)\n*   [事件日历](https://www.panewslab.com/zh/calendar)\n*   [专题](https://www.panewslab.com/zh/series)\n*   [导航](https://www.panewslab.com/zh/tools)\n*   [数据](https://www.panewslab.com/zh/padata/industry)\n*   发现\n\n[](https://www.panewslab.com/zh/search)\n\n### 单日ETH合约交易量Bybit排第一，同比增长354.01%\n\n[![Image 2: PA一线](https://image.panewslab.com/upload/image/20210202/S12ce6bd0b5c8479a8e53551c85d68ad7.jpg)](https://www.panewslab.com/zh/columns/166)\n\n[PA一线](https://www.panewslab.com/zh/columns/166)\n\nPANews 2月8日消息，据链上分析师 Ai 姨监测，ETH 24 小时合约交易量 Bybit 排名第一，高达 215.8 亿美元，同比增长 354.01%。市场猜测因 Bybit 做市商出问题导致凌晨价格出现异常波动。\n\n[此前消息](https://www.panewslab.com/zh/articles/019c3a96-b3c6-7775-8cdc-cc6a1c8e70cf)，BTC 和 ETH 在 00:05 开始的 10 几分钟内出现异常价格波动，多家交易所交易量异常放大。市场推测或与部分做市商的网格策略出错有关。\n\n[原文链接](https://x.com/ai_9684xtpa/status/2020380532509667370)\n\n分享至：\n\n作者：PA一线\n\n本内容只为提供市场信息，不构成投资建议。\n\n关注PANews官方账号，一起穿越牛熊\n\nPANews微信群\n\n[Telegram交流群](https://t.me/PANewsLab)[Telegram资讯频道](https://t.me/ChannelPANews)[@PANews](https://x.com/PANews)\n\n热搜:[比特币](https://www.panewslab.com/zh/search?query=%E6%AF%94%E7%89%B9%E5%B8%81)[以太坊](https://www.panewslab.com/zh/search?query=%E4%BB%A5%E5%A4%AA%E5%9D%8A)[稳定币](https://www.panewslab.com/zh/search?query=%E7%A8%B3%E5%AE%9A%E5%B8%81)[预测市场](https://www.panewslab.com/zh/search?query=%E9%A2%84%E6%B5%8B%E5%B8%82%E5%9C%BA)[特朗普](https://www.panewslab.com/zh/search?query=%E7%89%B9%E6%9C%97%E6%99%AE)[币安](https://www.panewslab.com/zh/search?query=%E5%B8%81%E5%AE%89)[OKX](https://www.panewslab.com/zh/search?query=OKX)[USDT](https://www.panewslab.com/zh/search?query=USDT)[DeFi](https://www.panewslab.com/zh/search?query=DeFi)[AI](https://www.panewslab.com/zh/search?query=AI)[美联储主席](https://www.panewslab.com/zh/search?query=%E7%BE%8E%E8%81%94%E5%82%A8%E4%B8%BB%E5%B8%AD)\n\n![Image 3](https://www.panewslab.com/_/assets/v2/static/subscribe-us-left.9ODLT9br.png)\n\n行业要闻\n\n市场热点\n\n精选读物\n\n[点击订阅](https://panewscn.substack.com/)\n\n![Image 4](https://www.panewslab.com/_/assets/v2/static/brand.DTYk2FHC.png)\n\n邮件订阅 订阅我们\n\nPANews\n\n[关于我们](https://www.panewslab.com/zh/about)[联系我们](mailto:panews@panony.com)[视觉文档](https://www.panewslab.com/brandingassets)[工作机会](https://panony.com/cn/col.jsp?id=111)[隐私政策](https://www.panewslab.com/zh/privacy-policy)[用户协议](https://www.panewslab.com/zh/user-agreement)\n\n推荐\n\n[事件日历](https://www.panewslab.com/zh/calendar/index.html)[热门活动](https://www.panewslab.com/zh/events)[RSS订阅](https://www.panewslab.com/zh/rss)[申请专栏](https://www.panewslab.com/zh/columns/apply)[行业数据](https://www.panewslab.com/zh/padata/industry)[工具导航](https://www.panewslab.com/zh/tools)\n\n下载APP\n\n[![Image 5](https://www.panewslab.com/_/assets/v2/static/dl-app-store.Y85Fwhjc.png)](https://apps.apple.com/cn/app/id1543133117)[![Image 6](https://www.panewslab.com/_/assets/v2/static/dl-google-play.Db0ECPXB.png)](https://play.google.com/store/apps/details?id=shanghai.panewsApp.com)[Android](https://assets.panewslab.com/panews-android.apk)\n\n关注我们\n\n[](https://x.com/PANews)[](https://t.me/ChannelPANews)[](https://t.me/PANewsLab)[](https://discord.com/invite/panewsdao)[](https://www.xiaohongshu.com/user/profile/6392f3930000000026004851)[](https://space.bilibili.com/455757159)[](https://www.xiaoyuzhoufm.com/podcast/633519d54eda304b8a9e1f0c)[](https://www.threads.com/@panews_lab)\n\n[@沪ICP备19004913号](https://beian.miit.gov.cn/#/)\n",
    "tags": [],
    "status": "success"
  },
  {
    "uuid": "884b692e20ec24304497441c033217a30a8c953b2e1580105838d24b68af3d75",
    "source": "PANews",
    "title": "Bithumb将于今日起发放补偿金",
    "original_url": "https://www.panewslab.com/zh/articles/019c3bd9-5711-7071-be8d-effe33e32e26",
    "publish_ts": 1770530520,
    "content_markdown": "Published Time: 2026-02-08T06:02:00.000Z\n\n[![Image 1](https://www.panewslab.com/_/assets/v2/static/brand.DTYk2FHC.png)](https://www.panewslab.com/zh)\n\n*   [首页](https://www.panewslab.com/zh)\n*   [深度](https://www.panewslab.com/zh/in-depth)\n*   [快讯](https://www.panewslab.com/zh/newsflash)\n*   [事件日历](https://www.panewslab.com/zh/calendar)\n*   [专题](https://www.panewslab.com/zh/series)\n*   [导航](https://www.panewslab.com/zh/tools)\n*   [数据](https://www.panewslab.com/zh/padata/industry)\n*   发现\n\n[](https://www.panewslab.com/zh/search)\n\n### Bithumb将于今日起发放补偿金\n\n[![Image 2: PA一线](https://image.panewslab.com/upload/image/20210202/S12ce6bd0b5c8479a8e53551c85d68ad7.jpg)](https://www.panewslab.com/zh/columns/166)\n\n[PA一线](https://www.panewslab.com/zh/columns/166)\n\nPANews 2月8日消息，针对比特币误发事件，Bithumb 发布事件应对进展公告，其已完成此前比特币误发事件的处置工作，当天已回收 99.7% 的误发放比特币，剩余 0.3% 的比特币（约 1,788 枚）因已被卖出，使用交易平台自有资产全额补齐。截至 2026 年 2 月 7 日 22:42:52，Bithumb 的比特币资产一致性恢复 100%。\n\n该事件的主要进展如下：\n\n*   2026-02-06 19:00：发生活动奖励超额支付\n*   2026-02-06 19:35：开始冻结超额支付账户的交易和提现\n*   2026-02-06 19:40：完成冻结超额支付账户的交易和提现，并开始追回工作\n*   2026-02-07 00:23：第一次通告（事件发生情况及初步措施进展）\n*   2026-02-07 04:30：第二次通告（事件原因及超额支付资产追回进展）\n*   2026-02-07 13:00：金融监督管理总局现场检查开始\n*   2026-02-07 17:33：第三次通知（公布防止再次发生及客户保护补偿方案）\n*   2026-02-07 22:42：已使用公司资产对售出的全部1,788枚比特币进行结算。\n\n此外，根据此前公布的补偿方案，补偿金将从今天开始按顺序发放。\n\n*   1) 对于事件发生时已登录Bithumb应用程序或网站的所有客户：将支付 2 万韩元。\n*   2) 向事件期间低价卖出比特币的用户补偿实际卖出差价 100% 以及额外 10% 安慰金。\n*   3) 所有交易品种免收交易手续费，为期7天（自 2026 年 2 月 9 日 00:00 起生效）。\n\n分享至：\n\n作者：PA一线\n\n本内容只为提供市场信息，不构成投资建议。\n\n关注PANews官方账号，一起穿越牛熊\n\nPANews微信群\n\n[Telegram交流群](https://t.me/PANewsLab)[Telegram资讯频道](https://t.me/ChannelPANews)[@PANews](https://x.com/PANews)\n\n热搜:[比特币](https://www.panewslab.com/zh/search?query=%E6%AF%94%E7%89%B9%E5%B8%81)[以太坊](https://www.panewslab.com/zh/search?query=%E4%BB%A5%E5%A4%AA%E5%9D%8A)[稳定币](https://www.panewslab.com/zh/search?query=%E7%A8%B3%E5%AE%9A%E5%B8%81)[预测市场](https://www.panewslab.com/zh/search?query=%E9%A2%84%E6%B5%8B%E5%B8%82%E5%9C%BA)[特朗普](https://www.panewslab.com/zh/search?query=%E7%89%B9%E6%9C%97%E6%99%AE)[币安](https://www.panewslab.com/zh/search?query=%E5%B8%81%E5%AE%89)[OKX](https://www.panewslab.com/zh/search?query=OKX)[USDT](https://www.panewslab.com/zh/search?query=USDT)[DeFi](https://www.panewslab.com/zh/search?query=DeFi)[AI](https://www.panewslab.com/zh/search?query=AI)[美联储主席](https://www.panewslab.com/zh/search?query=%E7%BE%8E%E8%81%94%E5%82%A8%E4%B8%BB%E5%B8%AD)\n\n![Image 3](https://www.panewslab.com/_/assets/v2/static/subscribe-us-left.9ODLT9br.png)\n\n行业要闻\n\n市场热点\n\n精选读物\n\n[点击订阅](https://panewscn.substack.com/)\n\n![Image 4](https://www.panewslab.com/_/assets/v2/static/brand.DTYk2FHC.png)\n\n邮件订阅 订阅我们\n\nPANews\n\n[关于我们](https://www.panewslab.com/zh/about)[联系我们](mailto:panews@panony.com)[视觉文档](https://www.panewslab.com/brandingassets)[工作机会](https://panony.com/cn/col.jsp?id=111)[隐私政策](https://www.panewslab.com/zh/privacy-policy)[用户协议](https://www.panewslab.com/zh/user-agreement)\n\n推荐\n\n[事件日历](https://www.panewslab.com/zh/calendar/index.html)[热门活动](https://www.panewslab.com/zh/events)[RSS订阅](https://www.panewslab.com/zh/rss)[申请专栏](https://www.panewslab.com/zh/columns/apply)[行业数据](https://www.panewslab.com/zh/padata/industry)[工具导航](https://www.panewslab.com/zh/tools)\n\n下载APP\n\n[![Image 5](https://www.panewslab.com/_/assets/v2/static/dl-app-store.Y85Fwhjc.png)](https://apps.apple.com/cn/app/id1543133117)[![Image 6](https://www.panewslab.com/_/assets/v2/static/dl-google-play.Db0ECPXB.png)](https://play.google.com/store/apps/details?id=shanghai.panewsApp.com)[Android](https://assets.panewslab.com/panews-android.apk)\n\n关注我们\n\n[](https://x.com/PANews)[](https://t.me/ChannelPANews)[](https://t.me/PANewsLab)[](https://discord.com/invite/panewsdao)[](https://www.xiaohongshu.com/user/profile/6392f3930000000026004851)[](https://space.bilibili.com/455757159)[](https://www.xiaoyuzhoufm.com/podcast/633519d54eda304b8a9e1f0c)[](https://www.threads.com/@panews_lab)\n\n[@沪ICP备19004913号](https://beian.miit.gov.cn/#/)\n",
    "tags": [],
    "status": "success"
  },
  {
    "uuid": "1d47b8b4eed83e9881d5cc79f1062adea2e36159be78f8f4b69e4ae6db29975d",
    "source": "ChainCatcher",
    "title": "AI 浪潮下的“局外人”突围：ARK 生态与其核心产品阿奇 AI 如何让普通人重掌技术红利？",
    "original_url": "https://www.chaincatcher.com/article/2244378",
    "publish_ts": 1770532442,
    "content_markdown": "",
    "tags": [
      "文章"
    ],
    "status": "partial_content"
  }
]