{
  "run_at_utc": "2026-02-24T05:36:27.972488+00:00",
  "window_hours": 4,
  "items": [
    {
      "source_name": "PANews",
      "title": "代币的下一站：一个有现金流的项目究竟需不需要发币?",
      "url": "https://www.panewslab.com/zh/articles/019c8a78-114e-734b-bbe7-6443ba757df5",
      "summary": "流水不争先，争的是滔滔不绝，我们该如何看待TGE与项目价值？",
      "publish_time_ts": 1771910820,
      "guid": "c97da13800135043ebc97c9bb61ffad815f6075a0e13af49b730af12e15b782f"
    },
    {
      "source_name": "ChainCatcher",
      "title": "数据：Coinbase 比特币溢价指数连续 40 日处于负溢价，创迄今最长 “连负” 纪录",
      "url": "https://www.chaincatcher.com/article/2247487",
      "summary": "ChainCatcher 消息，据市场消息，Coinbase 比特币溢价指数连续处于负溢价状态已达到 40 天，暂报 -0.0467%，创下该指标推出以来的最长 “连负” 纪录，超过 “1011 崩盘” 期间约 30 日的连续负溢价的天数。Coinbase 比特币溢价指数用于衡量 Coinbase（美国主流交易平台）上的比特币价格相对于全球市场平均价格的差异，负溢价通常反映美国市场卖压较大，投资者",
      "publish_time_ts": 1771910148,
      "guid": "b1fa5aa266ec73f0e1aa038e55708bc8d0588522d74ca449363674f23a3cf494"
    },
    {
      "source_name": "BlockBeats",
      "title": "WLFI风波发酵、ZachXBT预告内幕调查，海外币圈今天在聊啥？",
      "url": "https://m.theblockbeats.info/news/61311",
      "summary": "发布日期: 2025 年 2 月 24 日作者：BlockBeats 编辑部过去 24 小时，加密市场在多个维度呈现出明显分化的态势。主流话题集中于内幕交易调查预期与政治背景项目引发的信任争议；在生态层面，Solana 生态经历项目出清与舆论承压，Perp DEX 赛道一边推进新测试与融资扩张，另一边也面",
      "publish_time_ts": 1771909948,
      "guid": "17c64f0c8e7320b0b212856ec41766429bd352785a116e5810666f336f713477"
    },
    {
      "source_name": "ChainCatcher",
      "title": "数据：比特币现货 ETF 昨日总净流出 2.04 亿美元，贝莱德 IBIT 净流出 1.16 亿美元居首",
      "url": "https://www.chaincatcher.com/article/2247486",
      "summary": "ChainCatcher 消息，根据 SoSoValue 数据，比特币现货 ETF 总净流出 2.04 亿美元。\n\n昨日单日净流入最多的比特币现货 ETF 为 VanEck ETF HODL，单日净流入为 635.35 万美元，目前 HODL 历史总净流入达 11.29 亿美元。昨日单日净流出最多的比特币现货 ETF 为贝莱德 (Blackrock) ETF IBIT，单日净流出为 1.16 亿美",
      "publish_time_ts": 1771909810,
      "guid": "af825b1fbaf62f0b93a999a0cb613f88f70428e2402dad37ad64bde048bd9ee7"
    },
    {
      "source_name": "ChainCatcher",
      "title": "数据：以太坊现货 ETF 昨日总净流出 4947.66 万美元，贝莱德 ETHA 净流出 4537.79 万美元居首",
      "url": "https://www.chaincatcher.com/article/2247485",
      "summary": "ChainCatcher 消息，根据 SoSoValue 数据，以太坊现货 ETF 总净流出 4947.66 万美元。昨日单日净流出最多的以太坊现货 ETF 为贝莱德 ETF ETHA，单日净流出为 4537.79 万美元，目前 ETHA 历史总净流入达 118.3 亿美元。其次为 VanEck ETF ETHV，单日净流出为 271.22 万美元，目前 ETHV 历史总净流入达 1.73 亿美元",
      "publish_time_ts": 1771909792,
      "guid": "76a6de77e51d8a3452c988d4f82c0e650c831ea3a8abd371cb68ae630874e330"
    },
    {
      "source_name": "BlockBeats",
      "title": "比特币链上用户蒸发30%、ETF失血45亿美元：未来3个月怎么走？",
      "url": "https://m.theblockbeats.info/news/61310",
      "summary": "原文标题：Bitcoin looks busy but 31% of its users vanished as ETFs bleed $4.5B in 2026原文作者：Oluwapelumi Adejumo，CryptoSlate原文编译：深潮 TechFlow</blo",
      "publish_time_ts": 1771909589,
      "guid": "b94749fe5b52d239f3c1c989618e6bac7925a540f84d34716778824122b5d175"
    },
    {
      "source_name": "ChainCatcher",
      "title": "UPBIT 上线 Seeker (SKR) 并支持 KRW、BTC、USDT 交易",
      "url": "https://www.chaincatcher.com/article/2247484",
      "summary": "ChainCatcher 消息，UPBIT 将于 2025 年 2 月 24 日 16:00 上线 Seeker (SKR) 的交易，并支持 KRW、BTC、USDT 市场。用户可在公告发布后 1 小时 30 分钟内开始进行入金，交易将在上述时间正式开启。",
      "publish_time_ts": 1771909237,
      "guid": "f612af507c5b9cd3030e154802edc231e0c03d3b1b95e23b5c1fb95a1b88e144"
    },
    {
      "source_name": "ChainCatcher",
      "title": "BOT Chain 主网上线倒计时：模块化算法网络能否破解公链十年困局？",
      "url": "https://www.chaincatcher.com/article/2247482",
      "summary": "一条真正“不一样”的公链，正在撕开行业的裂缝。",
      "publish_time_ts": 1771908930,
      "guid": "9ab9446e7d4ad3b6512f098afc07a38d748dff00bcf49d9f623089db3b2bc5a1"
    },
    {
      "source_name": "ChainCatcher",
      "title": "香港一加密货币公司员工因涉嫌盗取客户 267 万枚 USDT 被捕",
      "url": "https://www.chaincatcher.com/article/2247483",
      "summary": "ChainCatcher 消息，香港警方逮捕了一名加密货币交易平台员工，该员工涉嫌盗取约 20 名客户共计 267 万枚 USDT，价值约 2,087 万港元。被捕者为该公司一名 34 岁姓蔡的网络工程师，在公司工作 4 年，主要负责管理移动应用程序。公司自今年 1 月初开始接到客户报告资金丢失，经调查发现该员工曾登入公司数据库并查看相关客户账户。案发地点位于尖沙咀科学馆道康宏广场南座的一家提供加",
      "publish_time_ts": 1771908591,
      "guid": "98a1ba73e7ee616c6b265244f74257b20f8a7070f5b964133e8cb4797a563065"
    },
    {
      "source_name": "ChainCatcher",
      "title": "嘉楠科技完成 3975 万美元收购 Cipher Mining 项目权益融资",
      "url": "https://www.chaincatcher.com/article/2247481",
      "summary": "ChainCatcher 消息，嘉楠科技宣布完成 3975 万美元融资，通过向 Cipher Mining 发行 806,439,900 股 A 类普通股（约 53,762,660 股 ADS）的方式，收购了其在西德克萨斯州三个比特币矿场项目中 49% 的股权。\n\n该项目主要业务是运营总电力容量为 120 MW、总算力约 4.4 EH/s 的比特币矿场。此次交易还包括嘉楠科技从 Cipher Mi",
      "publish_time_ts": 1771908234,
      "guid": "218278b37e88a188723f5ee5367506044e94d7a165bf48e68264499a9bf1378d"
    },
    {
      "source_name": "ChainCatcher",
      "title": "Binance Alpha 已上线英伟达代币化股票",
      "url": "https://www.chaincatcher.com/article/2247480",
      "summary": "ChainCatcher 消息，据官方页面显示，Binance Alpha 现已上线 Ondo 支持的英伟达代币化股票 NVDAon。",
      "publish_time_ts": 1771907706,
      "guid": "4f04eb3a4bfa14e81a6ca23398784b49f173b2046a1f121e7acd53f7b079e8fc"
    },
    {
      "source_name": "PANews",
      "title": "碳基文明的末代契约：“熵减意志”与“算力边界”",
      "url": "https://www.panewslab.com/zh/articles/019c8d80-418f-769b-8a05-5f6375ba943c",
      "summary": "我们不曾被取代，我们正在被放大。",
      "publish_time_ts": 1771907700,
      "guid": "a8cc0524f46662384954bafefac3cfcaa5ad61e8782bb59ec6beef144ec861ce"
    },
    {
      "source_name": "ChainCatcher",
      "title": "数据：当前加密恐慌贪婪指数为 9，处于极度恐慌状态",
      "url": "https://www.chaincatcher.com/article/2247479",
      "summary": "ChainCatcher 消息，据 Coinglass 数据显示，加密货币恐慌贪婪指数当前为 9，较昨日上涨 3 点。过去 7 天平均值为 8，过去 30 天平均值为 12。",
      "publish_time_ts": 1771907444,
      "guid": "9c38567a49c5cd98cc2f6edadfac992c389f4854fd44fcbadefe8c91a9916bcf"
    },
    {
      "source_name": "ChainCatcher",
      "title": "WLFI 的 FUD 闹剧，来自熊市敏感的神经",
      "url": "https://www.chaincatcher.com/article/2247478",
      "summary": "当前环境下，一点风吹草动都是风声鹤唳。",
      "publish_time_ts": 1771906969,
      "guid": "a555cd2a94636fe813135201d0f3e0407c5ab8ef2dc726725bf0f507b4723668"
    },
    {
      "source_name": "ChainCatcher",
      "title": "数据：BTC 跌破 63000 美元",
      "url": "https://www.chaincatcher.com/article/2247477",
      "summary": "ChainCatcher 消息，据 Gate 行情数据，BTC/USDT 现报 $63000，24 小时跌幅 3.11%。",
      "publish_time_ts": 1771906472,
      "guid": "9bebd25f0a5016f225055957fad7cfdeb366306900e1d24a198a6ffdba421914"
    },
    {
      "source_name": "Odaily",
      "title": "ETF 流出 45 亿美元：BTC 未来 3 个月还将继续下跌30%？",
      "url": "https://www.odaily.news/zh-CN/post/5209422",
      "summary": "交易量没有崩塌，但活跃地址六个月来持续萎缩，跌至五年最低点。这种\"表面繁荣、内部空洞\"的背离，是牛市结构性健康的反面信号。文章用 Glassnode、Santiment、CryptoQuant 三套数据交叉验证，提出三种未来情景，适合当下判断 BTC 走势的参考框架。<p",
      "publish_time_ts": 1771906023,
      "guid": "e27f74200963f26035eba7efa13853d25e3d5d49b5321001b1f866a44cdbf7ba"
    },
    {
      "source_name": "ChainCatcher",
      "title": "特朗普次子回应“删除 WLFI 推文”：一直在发布加密相关内容且两天前才出席过 WLFI 大会",
      "url": "https://www.chaincatcher.com/article/2247476",
      "summary": "ChainCatcher 消息，针对此前社区传闻特朗普次子 Eric Trump 删除了加密货币及 WLFI 相关推文，Eric Trump 首次给出正面回应，他在 X 平台上回复加密社区用户称发布相关内容的人就是个“小丑（clown）”，自己一直在发布加密货币相关推文，而且两天前刚刚出席了 World Liberty Fi 大会，并以“别犯傻（Don't be a fool）”回击质疑。",
      "publish_time_ts": 1771905881,
      "guid": "69f458daacd6c8c516cf0f207bd7fcfdc90dfbaaaf42ccff012fbd5862d77a97"
    },
    {
      "source_name": "ChainCatcher",
      "title": "数据：若 ETH 突破 1,922 美元，主流 CEX 累计空单清算强度将达 6.92 亿美元",
      "url": "https://www.chaincatcher.com/article/2247474",
      "summary": "ChainCatcher 消息，据 Coinglass 数据显示，若 ETH 突破 1,922 美元，主流 CEX 累计空单清算强度将达 6.92 亿美元。反之，若 ETH 跌破 1,748 美元，主流 CEX 累计多单清算强度将达 3.6 亿美元。",
      "publish_time_ts": 1771905627,
      "guid": "f2db8cc73e0ab4ba58b937ffa4d70231303c9d3e1280547af4f9624080403488"
    },
    {
      "source_name": "ChainCatcher",
      "title": "数据：若 BTC 突破 66,725 美元，主流 CEX 累计空单清算强度将达 13.62 亿美元",
      "url": "https://www.chaincatcher.com/article/2247473",
      "summary": "ChainCatcher 消息，据 Coinglass 数据显示，若 BTC 突破 66,725 美元，主流 CEX 累计空单清算强度将达 13.62 亿美元。反之，若 BTC 跌破 60,903 美元，主流 CEX 累计多单清算强度将达 7.21 亿美元。",
      "publish_time_ts": 1771905625,
      "guid": "e8a484c61f4edc4e54a970aed66c9a51e84f53284a49064822d18009a5470bec"
    },
    {
      "source_name": "PANews",
      "title": "ETH跌破1900美元！重挫22%背后，Vitalik的“五年紧缩”战略",
      "url": "https://www.panewslab.com/zh/articles/019c8d7b-49e7-711e-8ced-af2965a92cd8",
      "summary": "当前加密资产市场正经历剧烈的结构性调整。从最新的交易数据来看（如上方盘面所示，ETH/USDT 跌至 1,847.84 美元附近，近期单边下行趋势明显），以太坊（ETH）正在经历一场由资金面和预期面双重主导的深度回调。",
      "publish_time_ts": 1771905600,
      "guid": "c21ee37c442944ec8623911da6317dbb76f68bc272258fa5f7a43a0e4a10e50d"
    },
    {
      "source_name": "ChainCatcher",
      "title": "数据：贝莱德从 Coinbase 提取 2,086 枚比特币和 8,459 枚以太坊",
      "url": "https://www.chaincatcher.com/article/2247472",
      "summary": "ChainCatcher 消息，据链上分析师 The Data Nerd（@OnchainDataNerd）监测，贝莱德于今日从 Coinbase 提取了 2,086 枚比特币（约 1.35 亿美元）和 8,459 枚以太坊（约 1,584 万美元）。此次提取总价值约 1.5 亿美元。",
      "publish_time_ts": 1771905406,
      "guid": "26484a2c5e771b6aad7fb7b7a1e8721db8728076cde121a1a3739b22b69ab7db"
    },
    {
      "source_name": "Odaily",
      "title": "Crypto新出路：构建下一代无需许可新型银行",
      "url": "https://www.odaily.news/zh-CN/post/5209421",
      "summary": "编者按：十年前，金融科技新型银行通过移动应用改善了银行的使用体验，却并未改变资金运行的底层体系。今天，加密技术正在尝试触及更深层的变革，重构「钱是如何流动的」。本文从「存、花、增、借」四个维度出发，梳理了加密新型银行的发展路径与竞争格局：从自托管钱包与稳定币支付，到链上交易、借贷与收益机制。作者 Jay Yu（Pantera Capital 研究与投资团队成员）提出，以资金流转",
      "publish_time_ts": 1771905019,
      "guid": "27795a44a8f36b8b65150a857c82f985a88568c91b585162ca881b91656f49be"
    },
    {
      "source_name": "Odaily",
      "title": "RWA周报｜资产用户首次回撤明显；美SEC讨论代币化证券“渐进式”监管路径，拟推出创新豁免机制（2.15-2.24）",
      "url": "https://www.odaily.news/zh-CN/post/5209419",
      "summary": "原创 | Odaily 星球日报（@OdailyChina）作者 | Ethan（<a href=\"https://x.com/ethanzhan",
      "publish_time_ts": 1771904906,
      "guid": "b1d0131cb2b6ac77fcf62450ad4a07a751b64243bb8685bc2cfd8b866c257144"
    },
    {
      "source_name": "ChainCatcher",
      "title": "链上数据：约 101 万美元 ONDO 自 Coinbase 热钱包流入 Gate",
      "url": "https://www.chaincatcher.com/article/2247470",
      "summary": "ChainCatcher 消息，链上数据显示，2 月 24 日 02:38（UTC+8），标记为 Coinbase 热钱包的地址向 Gate 用户充值地址转入 4,079,141 枚 ONDO。按当时链上价格测算，该笔资产价值约 1,019,564 美元。",
      "publish_time_ts": 1771904597,
      "guid": "ef448d9889ea7621098b95261e17a31233b50b3b2e9ad6c58933a328b53c56b1"
    },
    {
      "source_name": "BlockBeats",
      "title": "年薪150万的工作，如何用500美元的AI完成？",
      "url": "https://m.theblockbeats.info/news/61308",
      "summary": "原文标题：《年薪 150 万的工作，我用 500 美金的 AI 完成：个人业务 Agent 升级指南》原文作者：XinGPT，加密研究员2026 年春节，我做了一个决定：把自己的全部业务流程 Agent 化。一周后的今天，这套系",
      "publish_time_ts": 1771904335,
      "guid": "e9028b0dcf4e86360e384249247e3333dfbc7347729668fda8698baf9c86cd53"
    },
    {
      "source_name": "ChainCatcher",
      "title": "数据：过去 24h Binance 净流入 2.27 亿 USDT",
      "url": "https://www.chaincatcher.com/article/2247469",
      "summary": "ChainCatcher 消息，据 Coinglass 数据显示，Binance 在过去 24 小时内净流入 2.27 亿 USDT。",
      "publish_time_ts": 1771904284,
      "guid": "f1f544b8ddc9b85bb17d0a68d887cb1fe40a064e86d0f800371b93f695d5dc87"
    },
    {
      "source_name": "ChainCatcher",
      "title": "数据：AGLD 24 小时跌超 35%，JST 涨超 6%",
      "url": "https://www.chaincatcher.com/article/2247468",
      "summary": "ChainCatcher 消息，据币安现货数据显示，市场出现大幅波动。AGLD 24 小时跌幅达 35.45%，JST 24 小时涨幅 6.06%，并触及今日新高。此外，GAS、MDT、PENGU 和 COOKIE 均出现“冲高回落”状态，分别跌幅 6.35%、9.37%、5.72% 和 6.82%。同时，ATOM 触及本周新低，跌幅 6.61%，CVX 则触及今日新低，跌幅 5.22%。",
      "publish_time_ts": 1771903825,
      "guid": "8045543a3bcc36bca6cc678e0b4f4e75d6f20e9a7178726ddc9e88b00376a38a"
    },
    {
      "source_name": "PANews",
      "title": "币安Alpha上线BSC代币化股票：Meta、苹果及谷歌等5个标的",
      "url": "https://www.panewslab.com/zh/articles/019c8dbd-ac64-77da-8852-83d9f09f4bdd",
      "summary": "PANews 2月24日消息，APP页面显示，币安Alpha已上线BSC链上代币化的亚马逊（AMZNON）、Meta（METAON）、苹果（AAPLON）、Circle（CRCLON）及谷歌（GOOGLON）股票。",
      "publish_time_ts": 1771903740,
      "guid": "ecc6599d04322ab33ec8dbb44a7a94fe2e03af389d330bd377a9e90f19a47ab0"
    },
    {
      "source_name": "ChainCatcher",
      "title": "钱志敏洗钱案跨国索赔超 12 万人，英国追偿将于 5 月 22 日截止登记",
      "url": "https://www.chaincatcher.com/article/2247467",
      "summary": "ChainCatcher 消息，据财新披露，2026 年 2 月 16 日与 17 日，英国高等法院举行了为期两天的钱志敏 6 万枚比特币洗钱案资产处置听证会，超 11300 名中国受害者拟向英国高院递交追偿申请，不过这仅占 128409 名受害者的 8.8%，英国追偿将于 5 月 22 日截止登记。\n\n据英国《犯罪所得法》（Proceeds of Crime Act，POCA）第 281 条，若",
      "publish_time_ts": 1771903054,
      "guid": "f103fbdd6e28f0507b6ef92205c030eb4d53db777c3da8a4968ef07a33ce4593"
    },
    {
      "source_name": "ChainCatcher",
      "title": "多资产交易热度升温，Gate 领跑持仓涨幅榜",
      "url": "https://www.chaincatcher.com/article/2247466",
      "summary": "ChainCatcher 消息，近日市场波动加剧，多资产合约交易活跃度显著提升。CoinGlass 数据显示，在 4 小时持仓涨幅榜中，TW88 持仓涨幅达 3653.99%，HK50 持仓涨幅 1671.68%，STEEM 涨幅 117.78%，UMA 涨幅 90.27%，LPT 涨幅 30.98%。Gate 平台的币种占据前两名，TW88 与 HK50 表现尤为突出，成为短时段内资金关注焦点。",
      "publish_time_ts": 1771902925,
      "guid": "aa06269d53f1dd8abd6c7207183b7830707292faeb95f130b5afeb335e8fbfc7"
    }
  ]
}