{
  "run_at_utc": "2026-06-04T05:03:46.307011+00:00",
  "window_hours": 4,
  "items": [
    {
      "source_name": "ChainCatcher",
      "title": "数据：SOL 生态代币 three 市值突破 1000 万美元，24 小时涨幅超 170%",
      "url": "https://www.chaincatcher.com/article/2269138",
      "summary": "ChainCatcher 消息，据 GMGN 数据，SOL 生态代币 three 市值一度突破 1,000 万美元，现报 1,069 万美元，24 小时涨幅超 170%据介绍，three 定位为浏览器原生 3D AI 代理，具备链上身份认证能力，并支持作为 Web 组件嵌入至任意网页场景据市场消息，该代币价格波动较大，投资者请注意风险。",
      "publish_time_ts": 1780547506,
      "guid": "32760c5ab72a587bd131c8e17ff79079e716f629121e7b7b671c405da0521713"
    },
    {
      "source_name": "ChainCatcher",
      "title": "Peter Schiff：USDT 市值终将超越比特币，BTC 短线在 6.1 万美元附近获得支撑",
      "url": "https://www.chaincatcher.com/article/2269137",
      "summary": "ChainCatcher 消息，据 BSCN 报道，比特币长期批评者 Peter Schiff 近日表示，Tether 的市值未来不仅将超过以太坊，最终还将超越比特币。他认为，唯一存在的不确定性并非结果，而是这一过程需要多长时间才能完成。Schiff 表示，随着稳定币在支付、交易结算以及数字美元流通中的应用不断扩大，市场对 USDT 的需求增长速度可能持续快于比特币等波动性资产。他坚持认为，比特币",
      "publish_time_ts": 1780547400,
      "guid": "31437eebe3414fbf3e2f18c388563648e03dfe1acde4633eef4a711f1d86c50a"
    },
    {
      "source_name": "ChainCatcher",
      "title": "Polymarket 上「马刺夺得 2026 NBA 总冠军」概率赛后下跌至 47%，OmenX 相关市场累计交易量达 1840 万美元",
      "url": "https://www.chaincatcher.com/article/2269136",
      "summary": "ChainCatcher 消息，2026 NBA 总决赛首场比赛中，在赛前市场普遍看好马刺队的情况下，马刺意外不敌尼克斯。Polymarket 上「马刺夺得 2026 NBA 总冠军」概率由赛前的 64% 跌至赛后的 47%，24 小时下跌 17%；「尼克斯夺冠」概率则升至 54%。\n\n与此同时，Base 原生杠杆预测市场 OmenX 上线 NBA 总冠军预测市场以来，该市场累计交易量已达 184",
      "publish_time_ts": 1780546740,
      "guid": "ab1df918d81fa0908df57f861158e3a86ade9aa24457f1da29758890c1f2c54e"
    },
    {
      "source_name": "ChainCatcher",
      "title": "火币HTX启动“用户关怀计划”：超千万美元福利致敬每一份信任",
      "url": "https://www.chaincatcher.com/article/2269135",
      "summary": "火币HTX正式启动千万级美元用户关怀计划，重磅派发100万份专属空投并推出十大场景权益活动，以真金白银回馈用户的长期陪伴",
      "publish_time_ts": 1780546585,
      "guid": "c4f3f82ca3d9b526dba6e9736e96a7ec752960f6f9a9e1aea202b1b419c3b773"
    },
    {
      "source_name": "ChainCatcher",
      "title": "数据：比特币现货 ETF 昨日总净流出 3.97 亿美元，持续 13 日净流出",
      "url": "https://www.chaincatcher.com/article/2269133",
      "summary": "ChainCatcher 消息，根据 SoSoValue 数据，昨日（美东时间 6 月 3 日）比特币现货 ETF 总净流出 3.97 亿美元。昨日单日净流出最多的比特币现货 ETF 为贝莱德 (Blackrock) ETF IBIT，单日净流出为 3.42 亿美元，目前 IBIT 历史总净流入达 626.36 亿美元。\n\n其次为富达 (Fidelity) ETF FBTC，单日净流出为 5425",
      "publish_time_ts": 1780545483,
      "guid": "76f11b06243d01b5ee3bfa692cf31beaa5a80fc3869d4d4e05b92c68171e963b"
    },
    {
      "source_name": "ChainCatcher",
      "title": "数据：以太坊现货 ETF 昨日总净流出 5293.6 万美元，持续 17 日净流出",
      "url": "https://www.chaincatcher.com/article/2269132",
      "summary": "ChainCatcher 消息，根据 SoSoValue 数据，美东时间 6 月 3 日，以太坊现货 ETF 总净流出 5293.6 万美元。\n\n昨日单日净流出最多的以太坊现货 ETF 为贝莱德（Blackrock） ETF ETHA，单日净流出为 5158.17 万美元，目前 ETHA 历史总净流入达 113.04 亿美元。\n\n其次为富达（Fidelity） ETF FETH，单日净流出为 13",
      "publish_time_ts": 1780545472,
      "guid": "f9c7de0a535d84adf75a16d11ed9b1e53d61c9238529b34fd55b4ea8134bafc1"
    },
    {
      "source_name": "PANews",
      "title": "比特币现货ETF昨日总净流出3.97亿美元，持续13日净流出",
      "url": "https://www.panewslab.com/zh/articles/019e90c7-17ea-72bc-b5af-e67c1b75d631",
      "summary": "PANews 6月4日消息，根据 SoSoValue 数据，昨日（美东时间 6 月 3 日）比特币现货 ETF 总净流出 3.97 亿美元。 昨日单日净流出最多的比特币现货 ETF 为贝莱德 (Blackrock） ETF IBIT，单日净流出为 3.42 亿美元，目前 IBIT 历史总净流入达 626.36 亿美元。 其次为富达 (Fidelity） ETF FBTC，单日净流出为 5425.5",
      "publish_time_ts": 1780545360,
      "guid": "0b93aede8f07295133e77d253164e9e6fc3199034bddb261481d5c91a6cef0a6"
    },
    {
      "source_name": "ChainCatcher",
      "title": "花旗：比特币下跌主因是缺乏新投资者需求，Strategy 卖币并非关键",
      "url": "https://www.chaincatcher.com/article/2269131",
      "summary": "ChainCatcher 消息，据 CoinDesk 报道，花旗（Citi）分析师 Alex Saunders 在最新报告中表示，Strategy 近期出售比特币虽引发市场波动，但更大问题在于缺乏新投资者需求。\n\n报告指出，Strategy 此次出售是此前已披露的税务优化计划的一部分，并非战略转变。真正值得关注的是，现货比特币 ETF 已连续 11 天净流出，这是投资者采用意愿疲软的重要信号。分析",
      "publish_time_ts": 1780545209,
      "guid": "945295c1885f09adc1e6a7a9c663a844fb726980975203c10dcadbbb20b56f75"
    },
    {
      "source_name": "ChainCatcher",
      "title": "台积电警告全球芯片供求紧张将持续数年，今年营收仍预计增长超 30%",
      "url": "https://www.chaincatcher.com/article/2269130",
      "summary": "ChainCatcher 消息，台积电在新竹举行年度股东大会上，董事长兼首席执行官魏哲家表示，全球芯片供应在未来数年仍将无法满足 AI 需求的激增。即便台积电在美国扩建产能，也难以完全满足美国客户的需求，实现供需平衡需要较长时间。\n\n魏哲家重申，台积电今年销售额仍预计增长超过 30%。公司今年资本支出预计接近 560 亿美元上限，而全球主要超大规模云服务商在 AI 领域支出预计达 7250 亿美元",
      "publish_time_ts": 1780544491,
      "guid": "38c0b6c3763f0a82936a22745208564eb4411de4ac5ba7caad7eab68247fb8bb"
    },
    {
      "source_name": "PANews",
      "title": "押注以太坊、Solana的加密VC Variant，现在把2.22亿押在AI上了",
      "url": "https://www.panewslab.com/zh/articles/019e90b9-b3a2-716d-84d4-569f5b549351",
      "summary": "从 Web3 到 AI Agent，老牌加密 VC Variant 2 亿元押注转型。",
      "publish_time_ts": 1780544340,
      "guid": "43a58fb67a44bd6742cbb5ea6ec02df603b9a5af35baf1af803e4a6fac1ec22b"
    },
    {
      "source_name": "ChainCatcher",
      "title": "Catcher Predict：“马斯克推文 2026 年 5 月 29 日至 6 月 5 日” “160-179” 胜率暴跌 15.55%",
      "url": "https://www.chaincatcher.com/article/2269128",
      "summary": "据 Catcher Predict 监测，预测市场 Polymarket 上“马斯克推文 2026 年 5 月 29 日至 6 月 5 日”事件中，子市场 “160-179” 的 “是” 选项胜率发生剧烈波动，由 1 小时前的 33.95% 暴跌至当前的 18.4%（波动幅度达 15.55%）。请注意相关突发消息影响。",
      "publish_time_ts": 1780543810,
      "guid": "88e735f90605ed23dbf1713a8c6afb6b268320b580e502f339564095b8bea79e"
    },
    {
      "source_name": "Odaily",
      "title": "以太坊的鲍尔默时刻：人人唱空时，流通盘正在消失",
      "url": "https://www.odaily.news/zh-CN/post/5211162",
      "summary": "原文作者：Ben Lakoff原文编译：深潮 TechFlow导读：当 Bankless 创始人清仓 ETH、19 岁开发者涌向 Solana 时，以太坊的熊市叙事已成共识。但 Ba",
      "publish_time_ts": 1780543200,
      "guid": "adbf87521b418c4a06695fd20203de431acc05f022bd20b36b87fd2621656406"
    },
    {
      "source_name": "ChainCatcher",
      "title": "Catcher Predict：“2026 NBA 总冠军” “纽约尼克斯” 胜率飙升 26.3%",
      "url": "https://www.chaincatcher.com/article/2269127",
      "summary": "据 Catcher Predict 监测，预测市场 Polymarket 上“2026 NBA 总冠军”事件中，子市场“纽约尼克斯”的“是”选项胜率发生剧烈波动，由 1 小时前的 29.15% 飙升至当前的 55.45%（波动幅度达 26.3%）。请注意相关突发消息影响。",
      "publish_time_ts": 1780542909,
      "guid": "bf965fa9cd3419cb392ebe4c91636441ceaeb9536c8ff613921e7392bc624fb9"
    },
    {
      "source_name": "ChainCatcher",
      "title": "数据：BTC 突破 64000 美元",
      "url": "https://www.chaincatcher.com/article/2269126",
      "summary": "ChainCatcher 消息，据 Gate 行情数据，BTC/USDT 现报 $64001.4，24 小时跌幅 3.66%。",
      "publish_time_ts": 1780542905,
      "guid": "e481384acb81a5911358779b2a370090a413cc4460463c7de018383b597006d1"
    },
    {
      "source_name": "ChainCatcher",
      "title": "SuperEx 上线 HPE、NOW 及 CRM U 本位永续合约",
      "url": "https://www.chaincatcher.com/article/2269125",
      "summary": "ChainCatcher 消息，加密交易平台 SuperEx 宣布于北京时间 6 月 4 日 11:00（03:00 UTC）正式上线 HPEUSDT、NOWUSDT 和 CRMUSDT U 本位永续合约交易对。\n\n据悉，上述新上线的合约交易对均支持全仓、逐仓及分仓模式，用户可通过 SuperEx 的 Web 端及 APP 端进行交易体验。",
      "publish_time_ts": 1780542903,
      "guid": "73b24d2c776f14ff9ccdfac53e6bf3cd2f8afbc5cdcbcd1fc09858cd5b0c34cb"
    },
    {
      "source_name": "PANews",
      "title": "李飞飞团队厘清“世界模型”概念，Sora只能算渲染器",
      "url": "https://www.panewslab.com/zh/articles/019e909e-b139-749b-a1c4-0b92a65535b9",
      "summary": "2026年6月，World Labs与李飞飞联合发布概念分类文章，直言“世界模型”是AI领域最被滥用的术语之一。一个视频生成器、一个自动驾驶预测网络、一个机器人控制模型，它们有什么共同点？几乎没有，但都被叫做“世界模型”。这篇文章没有发布新模型，而是回到POMDP理论源头，把所有系统归约为渲染器、模拟器、规划器三种功能投影。穿透营销话术，理解不同AI系统真实能力边界，这把钥匙终于有人递出来了。",
      "publish_time_ts": 1780542600,
      "guid": "c71b20e398271373f0f8d85aef56c89e8feac5520e7dfa34d28a4c2a628d6e7d"
    },
    {
      "source_name": "PANews",
      "title": "价值178万美元的稀有Casascius实物比特币在沉寂12年后被激活",
      "url": "https://www.panewslab.com/zh/articles/019e9098-9128-7751-976e-46a492b356cb",
      "summary": "PANews 6月4日消息，据CoinDesk报道，一枚来自2011-2013年稀有Casascius实物比特币于周三被激活，其全息防伪标签被揭开，存储的25枚BTC（价值约178万美元）被转移至新钱包。Casascius币由软件工程师Mike Caldwell创造，面额包括0.5、1、5、10、25、100甚至1000枚BTC，每枚币正面印有接收地址，私钥隐藏在背面防伪全息标签下。持有者可随时揭",
      "publish_time_ts": 1780542360,
      "guid": "fbe2c3e1a587d3e9445990da5cc34a41891a2205ce154be44fe86165f60bd851"
    },
    {
      "source_name": "ChainCatcher",
      "title": "数据：加密板块涨跌分化，AI 板块涨超 3.5%，BTC 跌破 6.3 万美元",
      "url": "https://www.chaincatcher.com/article/2269123",
      "summary": "ChainCatcher 消息，根据 SoSoValue 数据，加密市场板块涨跌分化，AI 板块 24 小时上涨 3.59%，板块内，Worldcoin（WLD）大幅上涨 22%，SkyAI（SKYAI）、Tagger（TAG）分别上涨 6.26%、10.28%。同时，DeFi 板块上涨 1.93%，Hyperliquid（HYPE）上涨 2.20%，盘中一度突破 75 美元，再度刷新历史新高，E",
      "publish_time_ts": 1780542173,
      "guid": "3c7a8ba4fcde961c4166ffd89d29f6b95a12bd2dd5f4b37010a8463830b9795a"
    },
    {
      "source_name": "ChainCatcher",
      "title": "RootData：IO 将于一周后解锁价值约 245 万美元的代币",
      "url": "https://www.chaincatcher.com/article/2269122",
      "summary": "ChainCatcher 消息，据Web3资产数据平台 RootData 代币解锁数据，io.net（IO）将于北京时间 06 月 11 日 0 时解锁约 1414 万枚代币，价值约 245 万美元。",
      "publish_time_ts": 1780542005,
      "guid": "8a3ad5706c7c3a515658e0262481247d27de1e314a1bf4014f421c580dff7b1c"
    },
    {
      "source_name": "ChainCatcher",
      "title": "RootData：MOCA 将于一周后解锁价值约 297 万美元的代币",
      "url": "https://www.chaincatcher.com/article/2269121",
      "summary": "ChainCatcher 消息，据Web3资产数据平台 RootData 代币解锁数据，Moca Network（MOCA）将于北京时间 06 月 11 日 0 时解锁约 27580 万枚代币，价值约 297 万美元。",
      "publish_time_ts": 1780542003,
      "guid": "ec3f96f406906bb3dfcc5984bb268b94b5c14e71be7ae33b70f2bce161daa5b9"
    },
    {
      "source_name": "ChainCatcher",
      "title": "RootData：ALLO 将于一周后解锁价值约 315 万美元的代币",
      "url": "https://www.chaincatcher.com/article/2269120",
      "summary": "ChainCatcher 消息，据Web3资产数据平台 RootData 代币解锁数据，Allora（ALLO）将于北京时间 06 月 11 日 0 时解锁约 1725 万枚代币，价值约 315 万美元。",
      "publish_time_ts": 1780542001,
      "guid": "57b2bb3c9976f6ae9a2b1c35f75046b4da38142902046024f67ca68ded850654"
    },
    {
      "source_name": "ChainCatcher",
      "title": "数据：上市公司 DDC Enterprise 增持 90 枚比特币，总持仓升至 2804 枚",
      "url": "https://www.chaincatcher.com/article/2269119",
      "summary": "ChainCatcher 消息，据 BitcoinTreasuries.NET 监测，美股上市公司 DDC Enterprise 增持 90 枚比特币，目前共持有 2804 枚 BTC，在比特币持仓排行榜中位列第 28 位。",
      "publish_time_ts": 1780541690,
      "guid": "0b3c3475b698dfc4fdc4a48792fcf7524373120f35c84a60690f2b91502e7f95"
    },
    {
      "source_name": "Odaily",
      "title": "一周千万，币圈套利者的美股新猎场",
      "url": "https://www.odaily.news/zh-CN/post/5211161",
      "summary": "期货、期权、差价合约，这些东西听起来就很专业。过去许多人总会认为衍生品是传统金融市场里门槛最高的玩法，但这些玩法在加密行业里越来越常见。最近一段时间的加密社区热议的除了美股标的本身之外，还有不少：「最近在&nbsp;<a href=\"https://app.hyperliquid.xyz/join/NTOD\" rel=\"noopener noreferrer\" t",
      "publish_time_ts": 1780541111,
      "guid": "0ee525d74230b95e44d5d87bad39a260ed00e70891c952f4a149ebb7bcb1888f"
    },
    {
      "source_name": "PANews",
      "title": "彭博社揭秘：中国富人是怎么突破每年5万限额，转移资产的？",
      "url": "https://www.panewslab.com/zh/articles/019e8ddd-9c2c-71cd-8435-4752b656aa9f",
      "summary": "中国外汇管制新规加码，1500亿美元灰色流出渠道曝光。彭博解析地下钱庄、蚂蚁搬家等五大路径，加密货币通道已被司法盯上。",
      "publish_time_ts": 1780541100,
      "guid": "7a090476f6f9eadd29fb18002d8112768b92dd2822a031fdb53e57a2fbf102c9"
    },
    {
      "source_name": "ChainCatcher",
      "title": "数据：7 Siblings 再次抄底 ETH，借入 1000 万 USDT 买入 5589 枚 ETH",
      "url": "https://www.chaincatcher.com/article/2269118",
      "summary": "ChainCatcher 消息，据 Lookonchain 监测，以 “逢市场暴跌抄底”闻名的巨鲸 7 Siblings 再度出手。约 1 小时前，其从 Spark 协议借入 1,000 万枚 USDT，随后以均价约 1,789 美元买入 5,589 枚 ETH，总价值约 1,000 万美元。",
      "publish_time_ts": 1780540918,
      "guid": "8e3aa55c18f28cdc99b3223b8225d95179644ca59c5819af46743be9ffda0c58"
    },
    {
      "source_name": "ChainCatcher",
      "title": "CFTC 跟进 SEC 废除\"不否认\"政策，加密执法和解规则迎来重大转变",
      "url": "https://www.chaincatcher.com/article/2269117",
      "summary": "ChainCatcher 消息，据 Cointelegraph 报道，美国商品期货交易委员会（CFTC）于 6月 4 日宣布废除实施近 30 年的\"不否认\"政策。该政策自 1998 年起要求被告在和解时承诺不公开否认 CFTC 的指控。\n\nCFTC 主席迈克·塞利格表示，此举与政府各监管机构的整体方向一致，并赋予委员会在执法和解中更大的灵活性。此前，SEC 已于 5 月率先废除类似政策。",
      "publish_time_ts": 1780540791,
      "guid": "a30dbd024f3e4ea9355dd187bbd6d29f272be59e446f290e1e42f01dd33312f5"
    },
    {
      "source_name": "PANews",
      "title": "昨夜今晨重要资讯（6月3日-6月4日）",
      "url": "https://www.panewslab.com/zh/articles/019e905c-1e01-739e-8338-dae75d013318",
      "summary": "贝莱德向Coinbase存入逾6000枚比特币，加密风险投资月度交易数量降至五年来最低水平，Stripe与Visa、Mastercard联手筹备稳定币平台。",
      "publish_time_ts": 1780540200,
      "guid": "7f73ea571cd4073740dc549a5f5e049c7effbaeb045897495e2b211b98a4156a"
    },
    {
      "source_name": "ChainCatcher",
      "title": "新股神 Serenity：今日以 6.2 万美元和 1750 美元买入 IBIT与 ETHA 做短线交易",
      "url": "https://www.chaincatcher.com/article/2269115",
      "summary": "ChainCatcher 消息，新股神 Serenity 在 X 平台发文表示，今日以比特币 62,000 及以太坊 1,750 的价格进行波段交易买入 IBIT 与 ETHA，强调此次操作为短线波段交易，而非长期持有。\n\nSerenity 指出，尽管他专注于波段操作，但市场价格下跌仍对 Robinhood（HOOD）、Coinbase（COIN）等相关股票产生负面影响。",
      "publish_time_ts": 1780540029,
      "guid": "da3e72f711b1ee2aaed74799fc29df6c97ff4892e7ef3792be7188cab8f43d04"
    },
    {
      "source_name": "ChainCatcher",
      "title": "数据：BTC 突破 63000 美元",
      "url": "https://www.chaincatcher.com/article/2269114",
      "summary": "ChainCatcher 消息，据 Gate 行情数据，BTC/USDT 现报 $63019，24 小时跌幅 5.48%。",
      "publish_time_ts": 1780539895,
      "guid": "0b5d6b48339ba86f8c17ba15247d60b8ecab90b6ac84172c9aa35e199783ddd1"
    },
    {
      "source_name": "ChainCatcher",
      "title": "Bitget UEX 日报｜美众院限特朗普对伊动武；比特币深度回调至6.3万美元；AI芯片供应危机凸显 (2026年06月04日)",
      "url": "https://www.chaincatcher.com/article/2269113",
      "summary": "Bitget UEX 日报",
      "publish_time_ts": 1780539663,
      "guid": "f46fd3eb2f00a344470cc49a89dbf9be3fa85fa0ba45e02af582b818c299a4be"
    },
    {
      "source_name": "PANews",
      "title": "过去24小时加密市场全网合约爆仓17.36亿美元，主爆多单",
      "url": "https://www.panewslab.com/zh/articles/019e906c-529b-73d9-818d-cd4e566cc984",
      "summary": "PANews 6月4日消息，Coinglass数据显示，过去24小时加密货币市场全网合约爆仓17.36亿美元，其中多单爆仓15.45亿美元，空单爆仓1.91亿美元。BTC爆仓总金额8.21亿美元，ETH爆仓总金额3.90亿美元。",
      "publish_time_ts": 1780539420,
      "guid": "319b7f112aea96070cbcb17a4fedbac73315e90e418cea276d559dc8fb5aeeda"
    },
    {
      "source_name": "ChainCatcher",
      "title": "数据：以太坊财库公司 FG Nexus 再次减持 1 万枚 ETH，约合 1816 万美元",
      "url": "https://www.chaincatcher.com/article/2269112",
      "summary": "ChainCatcher 消息，据链上分析师余烬监测，以太坊财库公司 FG Nexus 在 4 小时前将 1 万枚 ETH（1816 万美元）转入 Galaxy Digital。该公司因投资 ETH 亏损 8883 万美元：去年 8 至 9 月以 3940 美元均价花费 2 亿美元购入 5.06 万枚 ETH，自 11 月起开始减持，目前已减持 3.83 万枚 ETH（8917 万美元），均价 2",
      "publish_time_ts": 1780539353,
      "guid": "4f1848329da8359ececf87730f7ecd039a7c9deeb4c694b9e26db47341619ba6"
    },
    {
      "source_name": "ChainCatcher",
      "title": "Catcher Predict：“比特币 6 月 4 日突破” “62,000” 胜率暴跌 20.7%",
      "url": "https://www.chaincatcher.com/article/2269111",
      "summary": "据 Catcher Predict 监测，预测市场 Polymarket 上“比特币 6 月 4 日突破”事件中，子市场 “62,000” 的 “是” 选项胜率发生剧烈波动，由 1 小时前的 69.65% 暴跌至当前的 48.95%（波动幅度达 20.7%）。请注意相关突发消息影响。",
      "publish_time_ts": 1780539311,
      "guid": "1c86ffe218671ada8a1705ab18e67f92357c8a03a9734846f7776e3379f5e931"
    },
    {
      "source_name": "ChainCatcher",
      "title": "SoFi 成首家向零售用户提供银行发行稳定币的美国国家银行、Coinbase 获 CFTC 批准上线加密永续合约、Sequans 宣布彻底退出比特币储备战略现持 658 枚 BTC",
      "url": "https://www.chaincatcher.com/article/2269110",
      "summary": "ChainCatcher 消息，据 BBX 数据，昨日传统金融加密化与企业储备退出消息双线交织，核心动态如下：\n\nSoFi Technologies, Inc. (NASDAQ: $SOFI)通过 BusinessWire 官方新闻稿宣布，旗下 SoFiUSD 稳定币已在 SoFi 应用内正式向约 1,470 万会员开放，支持买入、卖出、持有与转换，成为美国历史上首家将自有稳定币内置于银行应用的国",
      "publish_time_ts": 1780538995,
      "guid": "31ea38ac706912728df2e1f63e349420204316c71d1d3fa15fe3e163af62df90"
    },
    {
      "source_name": "ChainCatcher",
      "title": "加密概念股每日观察：标准渣打加速收购 Zodia 托管业务，\"每家银行都将需要持有数字资产\"的论断正在从叙事走向行动",
      "url": "https://www.chaincatcher.com/article/2269109",
      "summary": "2026 年 6 月 4 日发布。CoinDesk 6 月 3 日报道，Zodia Custody CEO Julian Sawyer 确认，标准渣打 Standard Chartered PLC (LSE: $STAN) 对 Zodia 的全面收购正按计划推进，目标于 6 月底签约、8 月底完成；Sawyer 同日发表公开论断：\"每一家银行很快都将需要持有数字资产。\"这一表态，在 SoFi 银行",
      "publish_time_ts": 1780538979,
      "guid": "5dc6c13517d6712bcd860c1dee97f55bf50d3fb2cf106f02e2ffb73bcdda24e2"
    },
    {
      "source_name": "ChainCatcher",
      "title": "前 ConsenSys 大使 Russell Verbeeten 转移 2 万枚 ETH，部分 4144 枚已充值进交易所",
      "url": "https://www.chaincatcher.com/article/2269108",
      "summary": "ChainCatcher 消息，据链上分析师 Ai 姨监测，前 ConsenSys 大使 Russell Verbeeten (@rverbee) 时隔一年开始大额转移 ETH，其资金来源可追溯至 10 年前，成本低至 5.6 美元。7 小时前其从 Aave 提出 2.0426 万枚 ETH (3,726 万美元)，随后分发至 10 个新地址，其中一个地址的 4144 枚 ETH 已充值进 Coi",
      "publish_time_ts": 1780538874,
      "guid": "4874deb0060d016e95fcbb194eaeeb02802b2b76dd6cb7fddc4312aa8e704253"
    },
    {
      "source_name": "Odaily",
      "title": "24H热门币种与要闻｜HYPE价格超越SOL，后者跌至2023年以来最低水平；美媒称如何向伊朗“赔钱”成美伊谈判症结之一（6月4日）",
      "url": "https://www.odaily.news/zh-CN/post/5211160",
      "summary": "1、CEX 热门币种CEX 成交额 Top 10 及 24 小时涨跌幅：BTC: -6.96%ETH: -5.58%SOL: ",
      "publish_time_ts": 1780538748,
      "guid": "a4a6fb4c37fdc558fd24b8754d593a5e433457f16a545b658278a1be524a8033"
    },
    {
      "source_name": "ChainCatcher",
      "title": "数据：过去 12 小时全网爆仓 10.3 亿美元，主爆多单",
      "url": "https://www.chaincatcher.com/article/2269107",
      "summary": "ChainCatcher 消息，据 Coinglass 数据显示，过去 12 小时全网爆仓 10.3 亿美元，其中多单爆仓 9.52 亿美元，空单爆仓 7755 万美元。",
      "publish_time_ts": 1780538640,
      "guid": "86afd416cd93c8f5831263e7c2ce38c96749ad7041e6519b845ef3229e14060b"
    },
    {
      "source_name": "ChainCatcher",
      "title": "数据：BTC 跌破 62000 美元",
      "url": "https://www.chaincatcher.com/article/2269106",
      "summary": "ChainCatcher 消息，据 Gate 行情数据，BTC/USDT 现报 $61998，24 小时跌幅 7.33%。",
      "publish_time_ts": 1780538468,
      "guid": "d162dd6242f5dc4ac6f9b8ead7e487d40671522cf6284df06ee01932deb99a75"
    },
    {
      "source_name": "ChainCatcher",
      "title": "数据：BSC 链上 ATM 代币遭遇攻击，损失约 24.35 万美元",
      "url": "https://www.chaincatcher.com/article/2269105",
      "summary": "ChainCatcher 消息，据 TenArmorAlert 监测，BSC 链上 ATM 代币遭遇攻击，损失约 24.35 万美元。",
      "publish_time_ts": 1780538392,
      "guid": "aa96c76f2306d91a5768f231101279eac1d8dfe2c844f6b1fd89faa925ad3535"
    },
    {
      "source_name": "ChainCatcher",
      "title": "Peter Schiff：预计 STRC 投资者会损失大部分本金，Strategy 将会遭遇大量诉讼麻烦",
      "url": "https://www.chaincatcher.com/article/2269104",
      "summary": "ChainCatcher 消息，知名黄金支持者、加密货币仇视者 Peter Schiff 于 X 发文表示：“大多数 STRC 投资者最终可能会损失大部分资金，因为一旦 Michael Saylor 被迫取消股息派发，STRC 的价格最终将出现崩盘。\n\n届时，大量诉讼很可能会进一步加剧 Strategy（MSTR）所面临的问题。那些因误导性宣传而遭受损失的投资者，预计将通过法律途径寻求赔偿，以挽回",
      "publish_time_ts": 1780538385,
      "guid": "913bd96b5ec44fc87e2340d3162f83fb19e49f98b6b1c7f05840ba0c4145d66b"
    },
    {
      "source_name": "ChainCatcher",
      "title": "Drift 宣布重启为 Solana 生态 Perp DEX，收入用于设立用户赔付资金池",
      "url": "https://www.chaincatcher.com/article/2269103",
      "summary": "ChainCatcher 消息，Drift Protocol 表示，其当前首要任务是重启平台并恢复创收能力，以加快用户资金恢复进程。平台重启后将成为 Solana 上最大的 USDT 本位永续合约交易平台，相关收入将用于支持专门设立的用户赔付资金池。\n\nDrift 称，在 Tether 及其他合作伙伴提供的战略支持下，重启工作已取得实质性进展。为强化安全性，Drift 宣布任命前 Helium 协",
      "publish_time_ts": 1780538221,
      "guid": "7ab7e1ac2ea7c029ce3275478af58847fe5602cde202cceb0821cb3ceefa64bf"
    },
    {
      "source_name": "ChainCatcher",
      "title": "数据：Near Intents TVL 创新高，过去 7 天交易量超 6 亿美元",
      "url": "https://www.chaincatcher.com/article/2269102",
      "summary": "ChainCatcher 消息，Dune 数据显示，Near Intents TVL 昨日创下 2,260 万美元新高，现在已回落到 2,020 万美元。此外，Near Intents 累计交易量已突破 200 亿美元，其中过去 7 天交易量超 6 亿美元。",
      "publish_time_ts": 1780538091,
      "guid": "f747feaf853d494d092ad5a52da55d9e8955f9900f32ab1e35758b0fb0758ea6"
    },
    {
      "source_name": "ChainCatcher",
      "title": "数据：5 月比特币矿工总收入达 10.86 亿美元，创下四个月来新高",
      "url": "https://www.chaincatcher.com/article/2269101",
      "summary": "ChainCatcher 消息，据 Bitcoin.com 报道，5 月比特币矿工总收入达 10.86 亿美元，为 1 月以来首次突破 10 亿美元大关，其中区块补贴占 10.79 亿美元，交易费贡献微乎其微。然而随着比特币价格下跌，矿工面临盈利压力。算力已从 1000 EH/s 区间降至 975 EH/s 以下，每 PH/s 每日收入（算价）从一个月前的 37.44 美元降至约 30.77 美元",
      "publish_time_ts": 1780537732,
      "guid": "ca2a784ca2d3243eeef9c4997ad8f0db6010c5d74bc4d21b598b03db82540c51"
    },
    {
      "source_name": "PANews",
      "title": "交易所相继上线美股和RWA之后，效率才是币圈的核心竞争力",
      "url": "https://www.panewslab.com/zh/articles/019e8dd1-6b53-74f0-a940-e6081a2c90ce",
      "summary": "中心化交易所上线美股和 RWA，看起来是产品扩张，但更深一层，它是在重构甚至是挑战传统金融系统的运行方式。",
      "publish_time_ts": 1780537680,
      "guid": "6d40dcc1f1301dbd82033fa26efc4be00362bd385add638ececec3edce1ec6a7"
    },
    {
      "source_name": "ChainCatcher",
      "title": "数据：Hyperliquid 最大 ETH 多头浮亏扩大至 5800 万美元，清算价 1506 美元",
      "url": "https://www.chaincatcher.com/article/2269100",
      "summary": "ChainCatcher 消息，据余烬监测，随着 ETH 跌破 1800 美元，Hyperliquid 最大 ETH 多头持仓者以均价 2261 美元建立的 12 万枚 ETH 多头仓位目前账面浮亏已扩大至约 5800 万美元。为避免仓位被清算，其在过去 1 天内陆续补充 1100 万枚 USDC 保证金，将清算价格从 1617 美元降至 1506 美元。",
      "publish_time_ts": 1780537260,
      "guid": "48274aabc588c600487a0ecbc1e606c10392a5f672addc12109e6659a1b7f6fb"
    },
    {
      "source_name": "ChainCatcher",
      "title": "数据：持有 1.473 亿美元 ETH，某巨鲸沉寂 4 个月后借入 1000 万枚 USDT 买入 5589 枚 ETH",
      "url": "https://www.chaincatcher.com/article/2269099",
      "summary": "ChainCatcher 消息，据 Onchain Lens 监测，某巨鲸在沉寂 4 个月后借入 1,000 万枚 USDT，并以 1,789 美元价格买入 5,589 枚 ETH，目前持有 82,754 枚 ETH，价值 1.473 亿美元。",
      "publish_time_ts": 1780537186,
      "guid": "63dd6f2db832286efa91eac3d3a45164ca92e53084895afab10c70414f7f7ba0"
    },
    {
      "source_name": "ChainCatcher",
      "title": "Catcher Predict：“比特币 6 月价格预测” “62,500 美元” 胜率飙升 16%",
      "url": "https://www.chaincatcher.com/article/2269098",
      "summary": "据 Catcher Predict 监测，预测市场 Polymarket 上“比特币 6 月价格预测”事件中，子市场“62,500 美元”的“是”选项胜率发生剧烈波动，由 1 小时前的 79.5% 飙升至当前的 95.5%（波动幅度达 16%）。请注意相关突发消息影响。",
      "publish_time_ts": 1780536609,
      "guid": "e571c655cbb54b2d8d34b0281abdd9f3c09228491a7e23374d47a0d5db4fffd7"
    },
    {
      "source_name": "ChainCatcher",
      "title": "早报 | Coinbase Ventures 首次投资 ENA；SpaceX 拟在 IPO 中将每股定为 135 美元",
      "url": "https://www.chaincatcher.com/article/2268970",
      "summary": "6 月 03 日市场重要事件一览",
      "publish_time_ts": 1780536600,
      "guid": "23dc998dc39b52c7230fdd9d1300541080e6bab6e087b62a18b27094b6292c74"
    },
    {
      "source_name": "ChainCatcher",
      "title": "西班牙最大加密骗局 FX Winning 头目在迪拜被捕，涉案金额超 4.6 亿欧元",
      "url": "https://www.chaincatcher.com/article/2269097",
      "summary": "ChainCatcher 消息，据 CriptoNoticias 报道，西班牙公民 David Merino 因涉嫌领导加密庞氏骗局 FX Winning 在迪拜被捕。该骗局是西班牙调查史上最大的加密货币相关庞氏骗局，涉案金额超过 4.6 亿欧元，影响约 1.5 万名投资者。Merino 于 2021 年正式离开公司后从幕后运营该计划，通过承诺外汇和加密货币投资的高额回报来吸引资金，其运作模式为用",
      "publish_time_ts": 1780536355,
      "guid": "d5209cae4f9483e5bf641551f425225e85651f18acaf442f80c690fa1cc478a4"
    },
    {
      "source_name": "ChainCatcher",
      "title": "Polymarket 指控 Kalshi 涉嫌商业间谍活动，称多项产品发布“巧合过多”",
      "url": "https://www.chaincatcher.com/article/2269096",
      "summary": "ChainCatcher 消息，预测市场平台 Polymarket 认为竞争对手 Kalshi 可能对其纽约办公室及员工进行商业间谍活动。Polymarket 营销主管证实公司正在展开内部调查，并表示“巧合太多”，怀疑 Kalshi 存在不良意图。\n\n报道称，Polymarket 内部整理了一份名为“模仿者”的档案，记录约十余起可疑事件。其中包括 Polymarket 原计划于 2 月 12 日推",
      "publish_time_ts": 1780536167,
      "guid": "d37fba93f0bf0cf5aad0935240245c6fe10a0aa8af7d3e28f69b3d056a624e57"
    },
    {
      "source_name": "ChainCatcher",
      "title": "数据：SOL 跌破 70 美元",
      "url": "https://www.chaincatcher.com/article/2269095",
      "summary": "ChainCatcher 消息，据 Gate 行情数据，SOL/USDT 现报 $69.91，24 小时跌幅 6.55%。",
      "publish_time_ts": 1780535769,
      "guid": "8c8a1d024fa45d278a7b2565eb951aa92da0c404fefa3c615708ca290c796a7d"
    },
    {
      "source_name": "ChainCatcher",
      "title": "Catcher Predict：“巴尔的摩金莺对波士顿红袜” “让分 -1.5” 胜率飙升 29.95%",
      "url": "https://www.chaincatcher.com/article/2269093",
      "summary": "据 Catcher Predict 监测，预测市场 Polymarket 上“巴尔的摩金莺对波士顿红袜”事件中，子市场“让分 -1.5”的“波士顿红袜”选项胜率发生剧烈波动，由 1 小时前的 68% 飙升至当前的 97.95%（波动幅度达 29.95%）。请注意相关突发消息影响。",
      "publish_time_ts": 1780535708,
      "guid": "b627742ff89484c1228cf8ca881eb1794a211db1d49435154dbef91aed002733"
    },
    {
      "source_name": "ChainCatcher",
      "title": "派盾：稳定币 apxUSD 脱锚下跌 4.6% 至 0.94 美元，因抵押品价值缩水",
      "url": "https://www.chaincatcher.com/article/2269092",
      "summary": "ChainCatcher 消息，据派盾监测，由 STRC 等优先股支持的稳定币 apxUSD 跌至约 0.94 美元，跌幅 4.6%。随着 Bitcoin 跌至约 63,000 美元，抵押品价值缩水导致该稳定币脱锚。",
      "publish_time_ts": 1780535632,
      "guid": "fdee86d28f4532be1e2575052f69e05700989265cb78dcfcb6cb81d69e5d857e"
    },
    {
      "source_name": "ChainCatcher",
      "title": "数据：Abraxas Capital 继续减持 1469 枚 BTC，一天多累计减持 2469 枚 BTC",
      "url": "https://www.chaincatcher.com/article/2269091",
      "summary": "ChainCatcher 消息，据链上分析师余烬监测，加密资产管理机构 Abraxas Capital 继续减持 1,469 枚 BTC，将 1,469 枚 BTC（9,845 万美元）转进 Kraken 后提回 2,271 万枚 USDC。过去一天多时间里，其累计减持 2,469 枚 BTC（1.66 亿美元），均价 67,210 美元。",
      "publish_time_ts": 1780535333,
      "guid": "285f1e82644cb286cce07fde58aa0702c7d5d04563ec87cb2acb4b59ef8d31f9"
    },
    {
      "source_name": "ChainCatcher",
      "title": "俄罗斯财政部反对允许美元稳定币流通，拟优先发展卢布稳定币",
      "url": "https://www.chaincatcher.com/article/2269090",
      "summary": "ChainCatcher 消息，俄罗斯财政部副部长 Ivan Chebeskov 表示，不希望允许以美元计价的稳定币在俄罗斯市场流通。Chebeskov 指出，USDT 和 USDC 等外国稳定币发行方具备冻结用户钱包资产的能力。一旦相关钱包与俄罗斯央行许可的平台发生交易，持有者面临的资产冻结风险将显著上升。\n\n他透露，此前已有俄罗斯法人实体持有的美元稳定币被发行方冻结，而比特币和以太坊由于缺乏相",
      "publish_time_ts": 1780535210,
      "guid": "0befc0cced10699efa241cfbba1d110bda925aa6123fc61b0673bbfad15e1625"
    },
    {
      "source_name": "ChainCatcher",
      "title": "数据：美国 SOL 现货 ETF 单日总净流出 1274.29 万美元",
      "url": "https://www.chaincatcher.com/article/2269089",
      "summary": "ChainCatcher 消息，根据 SoSoValue 数据，昨日（美东时间 6 月 3 日）SOL 现货 ETF 单日总净流出 1274.29 万美元。\n\n昨日净流出最多的 SOL 现货 ETF 为 Bitwise Solana Staking ETF(BSOL)，单日净流出 1155.73 万美元，目前历史总净流入达 8.94 亿美元。\n\n\n其次为 Grayscale Solana Trus",
      "publish_time_ts": 1780534954,
      "guid": "32d1840a7ebc8f7bd1ee21b78bd7038f8e383a773518c82d28edb98238674546"
    },
    {
      "source_name": "ChainCatcher",
      "title": "数据：过去 1 小时全网爆仓达 1.98 亿美元，多单爆仓 1.83 亿美元",
      "url": "https://www.chaincatcher.com/article/2269088",
      "summary": "ChainCatcher 消息，据 CoinGlass 数据显示，过去 1 小时全网爆仓总金额达 1.98 亿美元。其中，多单爆仓 1.83 亿美元，空单爆仓 1492 万美元。",
      "publish_time_ts": 1780534837,
      "guid": "262dff34ed395ea548a75edc7c69b624e94d5375f2ccb97767aee46735a8fdc2"
    },
    {
      "source_name": "ChainCatcher",
      "title": "数据：Mt. Gox 前天移动的 116.3 枚 BTC 已于昨日转进 Bitstamp 交易所",
      "url": "https://www.chaincatcher.com/article/2269087",
      "summary": "ChainCatcher 消息，据链上分析师余烬监测，Mt. Gox 前天移动的 116.3 枚 BTC（825 万美元）已在昨天全部转进 Bitstamp 交易所。",
      "publish_time_ts": 1780534792,
      "guid": "449706e73ea5fa1f14305ec8722a4bfa0cbcf552842c9ffe3792b5de35538a60"
    },
    {
      "source_name": "ChainCatcher",
      "title": "数据：比特币跌破 63000 USDT",
      "url": "https://www.chaincatcher.com/article/2269086",
      "summary": "ChainCatcher 消息，据 Gate 行情数据显示，比特币跌破 63000 USDT，现报 62979.48 USDT，24H 跌幅为 5.35%。",
      "publish_time_ts": 1780534558,
      "guid": "419306d1aaf72fc9645d1f0102bcc5858ee0c6b5f86a56e285deb77d4815f9dd"
    },
    {
      "source_name": "ChainCatcher",
      "title": "数据：美国 BNB 现货 ETF 单日总净流入 121 万美元",
      "url": "https://www.chaincatcher.com/article/2269085",
      "summary": "ChainCatcher 消息，根据 SoSoValue 数据，昨日（美东时间 6 月 3 日）美国 BNB 现货 ETF 单日总净流入 121 万美元，全部来自 VanEck BNB ETF（VBNB）。截至发稿，BNB 现货 ETF 总资产净值为 219 万美元，历史累计净流入 121 万美元。",
      "publish_time_ts": 1780534493,
      "guid": "3342696a00670585f3af8525bed900daae913bf99d4e69a7c7101fb7ae747d31"
    },
    {
      "source_name": "PANews",
      "title": "嘉信理财推出全天候加密期货交易服务，涵盖BTC、ETH、SOL与XRP期货",
      "url": "https://www.panewslab.com/zh/articles/019e901e-1fe8-73eb-8832-7a6a1e9c9fda",
      "summary": "PANews 6月4日消息，据Bitcoin Magazine报道，嘉信理财（Charles Schwab）已推出全天候加密货币期货交易服务。其旗下专业级的在线交易平台thinkorswim现已支持比特币、以太坊、Solana和Ripple期货，每周近7天、每天近24小时可交易。",
      "publish_time_ts": 1780534320,
      "guid": "a19749601788dddf14c605c282462a11920d34b701f534368fcc4282fa1b49cd"
    },
    {
      "source_name": "ChainCatcher",
      "title": "数据：美国 HYPE 现货 ETF 单日总净流入 298.67 万美元",
      "url": "https://www.chaincatcher.com/article/2269082",
      "summary": "ChainCatcher 消息，根据 SoSoValue 数据，昨日（美东时间 6 月 3 日）HYPE 现货 ETF 单日总净流入 298.67 万美元。\n\n昨日仅 21Shares Hyperliquid ETF (THYP) 净流入，单日净流入 298.67 万美元，目前历史总净流入达 6020.07 万美元。\n\n截至发稿前，HYPE 现货 ETF 总资产净值为 1.92 亿美元，HYPE ",
      "publish_time_ts": 1780534082,
      "guid": "c15c0299b8b9d282998a2de99080a2ab2fe2e23e2aeeeaec4d70a2c3b386584e"
    },
    {
      "source_name": "PANews",
      "title": "大国封锁芯片，巨头买下核电站：为什么现在该认真看DeAI 了",
      "url": "https://www.panewslab.com/zh/articles/019e8de1-eeaf-746e-b078-190aa4465cb5",
      "summary": "美国芯片管制升级，华为Ascend 950PR量产，沙特、阿联酋疯狂买算力，肯尼亚数据中心被叫停。去中心化AI（DeAI）用区块链连接全球闲置GPU，能否打破寡头垄断？探索第三种可能。",
      "publish_time_ts": 1780534080,
      "guid": "d603fc4f63040ffa55ba43eaa7dc087de88beb9e9c92d41ef57c5cd33a9f6787"
    },
    {
      "source_name": "ChainCatcher",
      "title": "数据：美国 XRP 现货 ETF 单日总净流出 534.49 万美元",
      "url": "https://www.chaincatcher.com/article/2269081",
      "summary": "ChainCatcher 消息，根据 SoSoValue 数据，昨日（美东时间 6 月 3 日）XRP 现货 ETF 单日总净流出 534.49 万美元。\n\n昨日净流出最多的 XRP 现货 ETF 为 Bitwise XRP ETF (XRP)，单日净流出 405.61 万美元，目前历史总净流入达 4.67 亿美元。其次为 Grayscale XRP Trust ETF (GXRP)，单日净流出 ",
      "publish_time_ts": 1780534074,
      "guid": "796958ffa71c3e760ce44d4554189becf74bfcac19c4519d8714fbc9fc5a9f55"
    },
    {
      "source_name": "ChainCatcher",
      "title": "英国上议院发布 71 页稳定币监管报告，批评现行监管提案竞争力不足",
      "url": "https://www.chaincatcher.com/article/2269080",
      "summary": "ChainCatcher 消息，据英国上议院金融服务监管委员会发布报告《稳定币：等待监管》，全球稳定币市值已超 3100 亿美元，但英国英镑稳定币市场仍处于起步阶段，监管框架建设明显落后于美国（GENIUS 法案）和欧盟（MiCAR）。\n\n报告对英国金融行为监管局（FCA）及英格兰银行现行监管提案提出多项批评，重点包括：\n\n• 英格兰银行要求系统性稳定币发行商将至少 40% 储备资产存入无息央行存",
      "publish_time_ts": 1780533826,
      "guid": "fd017ddfdc749ff0cece3ffa728cc5ab8062f2f6def8859e0682edcbc3c31ca0"
    },
    {
      "source_name": "Odaily",
      "title": "Outpoll评测：一个面向活跃交易者打造的预测市场平台",
      "url": "https://www.odaily.news/zh-CN/post/5211159",
      "summary": "过去两年，预测市场正从小众赛道走向主流视野。交易量迈入数十亿美元级别，机构资本开始入场，市场价格也越来越多地被拿来与民调和专家预测相互参照。相比之下，预测市场的交易体验和工具层却没有同步升级。<str",
      "publish_time_ts": 1780533501,
      "guid": "88ee479d55537be440dc78d31ff48f89d1e76684679ff184921b0d7c22fd382b"
    },
    {
      "source_name": "ChainCatcher",
      "title": "数据：巨鲸 pension-usdt.eth 平仓 BTC 空单盈利 356 万美元，新开 ETH 空单浮盈 450 万美元",
      "url": "https://www.chaincatcher.com/article/2269079",
      "summary": "ChainCatcher 消息，据 Onchain Lens 监测，巨鲸 “pension-usdt.eth” 已完全平掉 BTC 空头仓位，盈利 356 万美元。其新开了 5 万枚 ETH 的 3 倍空头仓位（价值 8,900 万美元），已浮盈超过 450 万美元，总盈利超过 3960 万美元。",
      "publish_time_ts": 1780533293,
      "guid": "466cf9a8dfe4557d83e8ee83f819e9408f8ddc131edfb4c50ff2f3b3204e6203"
    },
    {
      "source_name": "ChainCatcher",
      "title": "灰度向美国 SEC 提交 BNB ETF 第三版 S-1 修订文件，代码为 GBNB",
      "url": "https://www.chaincatcher.com/article/2269078",
      "summary": "ChainCatcher 消息，彭博 ETF 分析师 James Seyffart 在 X 平台发文称，灰度已向美国证券交易委员会（SEC）提交其 BNB ETF 第三版 S-1 修订文件，代码为 GBNB，费用尚未公布。",
      "publish_time_ts": 1780533174,
      "guid": "f7887ae3d33ee3c98486383f7b0c701287d198aebb1bb1f3b11322fcce225c07"
    },
    {
      "source_name": "ChainCatcher",
      "title": "数据：James Wynn 以 40 倍杠杆开设 2.65 枚 BTC 空单，清算价为 66628.7 美元",
      "url": "https://www.chaincatcher.com/article/2269077",
      "summary": "ChainCatcher 消息，据 Lookonchain 监测，James Wynn 回归，以 66,703.1 美元的价格开设了 2.65 枚 BTC（16.9 万美元）的 40 倍空头仓位，清算价为 66,628.7 美元。",
      "publish_time_ts": 1780533054,
      "guid": "f6835c3510e0a8220a462351581d7abddcc91ba435bef9e123a845e9997e62aa"
    },
    {
      "source_name": "ChainCatcher",
      "title": "嘉信理财高管：比特币并非因 Saylor 而崩盘，而是失去动量交易主导地位",
      "url": "https://www.chaincatcher.com/article/2269076",
      "summary": "ChainCatcher 消息，据 CoinDesk 报道，嘉信理财数字资产研究总监 Jim Ferraioli 表示，比特币近期走弱并非因机构需求消退或 Michael Saylor 卖出比特币，而是正在失去市场主导动量交易的地位。其指出，加密投资者历来追随动量，而目前动量已离开加密领域。资金正流向人工智能相关股票和 IPO 等热门叙事，SpaceX 的 IPO 可能估值达 1.8 万亿美元，一",
      "publish_time_ts": 1780532874,
      "guid": "8d6cc5510f8526f149bed3c69cc561e2809d596347423346379dfcf7678ca63f"
    },
    {
      "source_name": "ChainCatcher",
      "title": "数据：若 Bitcoin 跌破 6.2 万美元，主流 CEX 累计多单清算强度将达 6.09 亿",
      "url": "https://www.chaincatcher.com/article/2269075",
      "summary": "ChainCatcher 消息，据 Coinglass 数据，若 Bitcoin 跌破 6.2 万美元，主流 CEX 累计多单清算强度将达 6.09 亿。反之，若 Bitcoin 突破 6.6 万美元，主流 CEX 累计空单清算强度将达 3.76 亿。清算图并不是展示精确的待清算的合约数目，或者精确的被清算的合约价值。清算图上的柱子展示的是其实是每个清算簇相对临近清算簇的重要性，即强度。因此，清算",
      "publish_time_ts": 1780532819,
      "guid": "23122a59a8d0a4a1c67b5cb11ff584efc1cd8d1e9d9268c9bb1e14378607b4e6"
    },
    {
      "source_name": "ChainCatcher",
      "title": "Catcher Predict：“Knicks vs. Spurs” 巨鲸单笔 130,179.12 美元买入 “Knicks vs. Spurs”",
      "url": "https://www.chaincatcher.com/article/2269074",
      "summary": "据 Catcher Predict 监测链上数据，预测市场 Polymarket 上发生大额资金异动。有巨鲸资金在 “Knicks vs. Spurs” 事件中，针对 “Knicks vs. Spurs” 单笔买入了 130,179.12 美元。以当前成交单价计算，该标的最新对应胜率为 37%。",
      "publish_time_ts": 1780532709,
      "guid": "077dfda7e6e635449b44a10553e30a25c64aebe66a89ab265d607221eb93c40b"
    },
    {
      "source_name": "ChainCatcher",
      "title": "数据：BTC 跌破 64000 美元",
      "url": "https://www.chaincatcher.com/article/2269072",
      "summary": "ChainCatcher 消息，据 Gate 行情数据，BTC/USDT 现报 $63986.4，24 小时跌幅 4.26%。",
      "publish_time_ts": 1780532689,
      "guid": "e75dc9c459cab48a24485606b3dcf8b47d79c5342e793ade17d109d5e8d42753"
    },
    {
      "source_name": "ChainCatcher",
      "title": "Bitmine 宣布发行优先股拟募资 3 亿美元",
      "url": "https://www.chaincatcher.com/article/2269071",
      "summary": "ChainCatcher 消息，Bitmine Immersion Technologies 宣布拟发行 300 万股 9.50% A 系列永续优先股，每股面值 100 美元，预计募资总额 3 亿美元。该优先股初始清算优先权为每股 100 美元，并将按年化 9.5%利率累计派发股息，以现金形式按周支付；即使公司未宣布分红或暂时缺乏可分配资金，股息仍将持续累积。\n\nBitmine 拥有提前赎回权，发",
      "publish_time_ts": 1780531903,
      "guid": "21995f39748f2772c8debd74dda1ed6544ec46350e68bcd69674bec4f74b1bc1"
    },
    {
      "source_name": "ChainCatcher",
      "title": "加密 VC 月度交易数量跌至五年低点，资本向头部项目集中",
      "url": "https://www.chaincatcher.com/article/2269070",
      "summary": "ChainCatcher 消息，据 The Block 报道，加密风险投资月度交易数量降至约 50 笔，为 2021 年前以来最低水平。基础设施与加密金融服务两大历史最活跃赛道均跌至多年低点。投资者注意力大规模转向 AI 赛道，叠加早期优质项目供给不足，是本轮交易数量萎缩的主要原因。\n\n尽管交易笔数下滑，融资总额仍维持相对高位，呈现“少笔大额”特征——预测市场平台 Kalshi 近期完成 10 亿",
      "publish_time_ts": 1780531665,
      "guid": "e228dda2b17791f5ca04546b9f0264a5393afe7630ab68a3cd5afeec65c028eb"
    },
    {
      "source_name": "PANews",
      "title": "美众议院通过决议，限制特朗普对伊动武权力",
      "url": "https://www.panewslab.com/zh/articles/019e8ff1-7990-7036-9cba-e6fdd1cd3fad",
      "summary": "PANews 6月4日消息，据金十报道，由共和党控制的美国众议院投票决定叫停美国对伊朗的战争，在这一不受欢迎且正给美国民众带来日益沉重经济负担的对外冲突问题上，众议院与特朗普分道扬镳。该决议案以215票对208票获得通过，投票结果显示，有四名共和党议员打破党派界限，与全体民主党议员一道投下了赞成票。这表明对这场战争的担忧正开始在特朗普所属的党派内部蔓延。该决议案要求特朗普将美军撤出针对伊朗的敌对行",
      "publish_time_ts": 1780531560,
      "guid": "1fbf26a4547ac82f033fc761ab9e10f94ba2351400d85dc4cf5373b24bf78867"
    },
    {
      "source_name": "PANews",
      "title": "SpaceX官方拟定IPO发行价为135美元，估值达1.77万亿美元",
      "url": "https://www.panewslab.com/zh/articles/019e8ff1-2e1a-7444-857a-f9b02dbe2d82",
      "summary": "PANews 6月4日消息，据格隆汇报道，马斯克旗下的SpaceX公司周三向美国证交会（SEC）提交的一份文件中披露，该公司计划在正式启动IPO推介工作之前，将发行价格固定在每股135美元（与消息人士透露的价格一致）。SpaceX表示，公司计划发行5.556亿股股票，以此筹集750亿美元资金。通常情况下，在IPO流程的这一阶段，发行方往往会设定一个价格区间，以便其能够测试市场在不同价格水平下的需求",
      "publish_time_ts": 1780531500,
      "guid": "1b475c3ff96cff56d20981e29e0d27f329a3c8da283b21c429e9be3c8706d153"
    },
    {
      "source_name": "PANews",
      "title": "美联储褐皮书：通胀挤压美国消费者和企业，油价冲击已传导至各个领域",
      "url": "https://www.panewslab.com/zh/articles/019e8ff0-9cb4-77ea-bbb6-0d054e47dda7",
      "summary": "PANews 6月4日消息，据财联社报道，美联储周三公布的褐皮书显示，尽管AI投资热潮仍在延续，但美国经济已显现消费承压、招聘疲软及物价上涨等迹象。数据显示，在12个联储辖区中，有10个地区经济活动以“轻微至温和”的速度增长，1个地区小幅下降，1个地区保持不变。报告显示，企业对未来六个月的展望总体变化不大，但持续高企的不确定性以及消费者支出放缓的迹象，正在拖累市场情绪，企业预计经济增长前景不会出现",
      "publish_time_ts": 1780531440,
      "guid": "5879b387d3d000224912bb91f8a55b1a40aa539a152390c20f2bee8e4106734e"
    },
    {
      "source_name": "ChainCatcher",
      "title": "Hyperliquid 的 HYPE 价格超越 Solana，SOL 价格跌至 2023 年以来最低水平",
      "url": "https://www.chaincatcher.com/article/2269068",
      "summary": "ChainCatcher 消息，据 The Block 报道，Hyperliquid 的 HYPE 代币价格于周三超越 Solana，后者跌至 2023 年以来最低水平。HYPE 周二创下 74.67 美元历史新高，目前交易价格为 74.47 美元，高于 Solana 的 71.62 美元。过去一个月 HYPE 上涨约 24%，是前 20 大加密资产中少数上涨的品种，同期 Solana 下跌近 1",
      "publish_time_ts": 1780531265,
      "guid": "2b7ad7acea9690966e40b007effc5102ddbb2d5d7114c91d385ed5e23e110c3f"
    },
    {
      "source_name": "ChainCatcher",
      "title": "Catcher Predict：“圣地亚哥教士对费城费城人” “圣地亚哥教士对费城费城人” 胜率暴跌 15%",
      "url": "https://www.chaincatcher.com/article/2269067",
      "summary": "据 Catcher Predict 监测，预测市场 Polymarket 上“圣地亚哥教士对费城费城人”事件中，子市场“圣地亚哥教士对费城费城人”的“圣地亚哥教士”选项胜率发生剧烈波动，由 1 小时前的 33.5% 暴跌至当前的 18.5%（波动幅度达 15%）。请注意相关突发消息影响。",
      "publish_time_ts": 1780531207,
      "guid": "5d061a00684a57ee9b3d3f923502870bfb214878c9e1cf9fe5cbe71dcacea546"
    },
    {
      "source_name": "PANews",
      "title": "Hyperliquid的HYPE价格超越Solana，SOL价格跌至2023年以来最低水平",
      "url": "https://www.panewslab.com/zh/articles/019e8fee-530b-73f8-9316-181bddd14e85",
      "summary": "PANews 6月4日消息，据The Block报道，Hyperliquid的HYPE代币价格于周三超越Solana，后者跌至2023年以来最低水平。HYPE周二创下74.67美元历史新高，目前交易价格为74.47美元，高于Solana的71.62美元。过去一个月HYPE上涨约24%，是前20大加密资产中少数上涨的品种，同期Solana下跌近14%。按市值计算，Solana仍以约420亿美元领先于",
      "publish_time_ts": 1780531200,
      "guid": "eaf7843578b4bf12730edd47fdcca6d1408a6c01f0e264143ed4b7c960242c55"
    },
    {
      "source_name": "PANews",
      "title": "Bitwise：Crypto沦为逆向投资，三个逻辑看懂当前市场",
      "url": "https://www.panewslab.com/zh/articles/019e8cfd-d53a-77fd-812e-2b3946981d62",
      "summary": "加密市场惨淡，比特币跌21%以太坊跌33%，逆向投资逻辑主导，资金转向Hyperliquid等基本面标的。CLARITY法案悬而未决，耐心布局正当时。",
      "publish_time_ts": 1780530900,
      "guid": "dce6ecb0501587e8958593d09b90e60c36c18cef74f22975886d110f5f1e8d27"
    },
    {
      "source_name": "ChainCatcher",
      "title": "Catcher Predict：“Knicks vs. Spurs” 巨鲸单笔 55197.46 美元买入 “Spread -4.5”",
      "url": "https://www.chaincatcher.com/article/2269066",
      "summary": "据 Catcher Predict 监测链上数据，预测市场 Polymarket 上发生大额资金异动。有巨鲸资金在 “Knicks vs. Spurs” 事件中，针对 “Spread -4.5” 单笔买入了 55197.46 美元。以当前成交单价计算，该标的最新对应胜率为 48%。",
      "publish_time_ts": 1780528808,
      "guid": "c7f5000f615fbd747ccb6153e0c861f885ec7a87f1fbf7cc0c87656ef293608c"
    },
    {
      "source_name": "ChainCatcher",
      "title": "美联储 6 月维持利率不变概率达 98.4%，7 月加息概率 8.4%",
      "url": "https://www.chaincatcher.com/article/2269065",
      "summary": "ChainCatcher 消息，据金十报道，CME “美联储观察”显示，美联储到 6 月维持利率不变的概率为 98.4%，累计降息 25 个基点的概率为 1.6%。到 7 月，维持利率不变的概率为 90.2%，累计加息 25 个基点的概率为 8.4%，累计降息 25 个基点的概率为 1.4%。",
      "publish_time_ts": 1780524938,
      "guid": "4a17a42e809b6ebfd910f8035b77875af6e60b9da6427a69255f42a31719356b"
    },
    {
      "source_name": "ChainCatcher",
      "title": "Catcher Predict：“Knicks vs. Spurs” “Devin Vassell O/U 2.5” 胜率暴跌 32%",
      "url": "https://www.chaincatcher.com/article/2269064",
      "summary": "据 Catcher Predict 监测，预测市场 Polymarket 上“Knicks vs. Spurs”事件中，子市场 “Devin Vassell O/U 2.5” 的 “Over” 选项胜率发生剧烈波动，由 1 小时前的 86% 暴跌至当前的 54%（波动幅度达 32%）。请注意相关突发消息影响。",
      "publish_time_ts": 1780524010,
      "guid": "48ac67f9bda19189ba1a38ff14669536ce7eed524ce590ac4d453da8b0f4a908"
    },
    {
      "source_name": "ChainCatcher",
      "title": "Catcher Predict：“Knicks vs. Spurs” 巨鲸单笔 109,561.76 美元买入 “Knicks vs. Spurs”",
      "url": "https://www.chaincatcher.com/article/2269063",
      "summary": "据 Catcher Predict 监测链上数据，预测市场 Polymarket 上发生大额资金异动。有巨鲸资金在 “Knicks vs. Spurs” 事件中，针对 “Knicks vs. Spurs” 单笔买入了 109,561.76 美元。以当前成交单价计算，该标的最新对应胜率为 37%",
      "publish_time_ts": 1780522211,
      "guid": "6ae9de638df4ce20f12f4ca01458fac7bb44418f08b9a8bf8f9e5383150e94bc"
    }
  ]
}